Workbook

Sheet Estimate
A2: Ulta Beauty Fresno DC New RTUs R6 | C2: Date: 11/11/2025
A3: The Alleato Group . 8383 Craig Street #150 . Indianapolis, IN . 46250
A5: Contact | B5: Brandon Clymer | C5: bclymer@alleatogroup.com | D5: 317.760.0088
A6: Contact | B6: AJ Taylor | C6: ataylor@alleatogroup.com | D6: 317.363.3396
A7: Project: | B7: =A2 -> Ulta Beauty Fresno DC New RTUs R6
A8: Location: | B8: 850 East Central Avenue, Fresno, CA 93725
A10: Division 01 General Conditions
A11: Total | B11: ='General Conditions'!C27 -> 163252
A12: Division 02 Existing Conditions
B13: =QuantityTakeoff!Y23 -> 0 | C13: From Qty Sheet
B14: 0
A15: Total | B15: =SUBTOTAL(9,B13:B14) -> 0
A16: Division 03 Concrete
B17: =QuantityTakeoff!Y26 -> 0 | C17: From Qty Sheet
B18: 0
A19: Total | B19: =SUBTOTAL(9,B17:B18) -> 0
A20: Division 03.1 Precast
A21: Precast | C21: ATMI
A23: Total | B23: =SUBTOTAL(9,B21:B22) -> 0
A24: Division 04 Masonry
A25: Masonry | B25: =QuantityTakeoff!Y33 -> 0 | C25: From Qty Sheet
B26: 0
A27: Total | B27: =SUBTOTAL(9,B25:B26) -> 0
A28: Division 05 Metals
B29: =QuantityTakeoff!Y36 -> 247500 | C29: From Qty Sheet
B30: 0
B31: 0
A32: Total | B32: =SUBTOTAL(9,B29:B30) -> 247500
A33: Division 06 Wood Plastics Composits
B34: =QuantityTakeoff!Y41 -> 0 | C34: From Qty Sheet
B35: 0
A36: Total | B36: =SUBTOTAL(9,B34:B35) -> 0
A37: Division 07 Thermal and Moisture Protection
B38: =QuantityTakeoff!Y49 -> 72000 | C38: From Qty Sheet
B39: 0
B40: 0
B41: 0
A42: Total | B42: =SUBTOTAL(9,B38:B41) -> 72000
A43: Division 08 Openings
B44: =QuantityTakeoff!Y60 -> 0
B45: 0
B46: 0
B47: 0
A48: Total | B48: =SUBTOTAL(9,B44:B47) -> 0
A49: Division 09 Finishes
B50: 0
B51: =QuantityTakeoff!Y67 -> 0
A52: Tax
B53: 0
B54: 0
B55: 0
A56: Total | B56: =ROUNDUP(SUBTOTAL(9,B50:B55), 0) -> 0
A57: Division 10 Specialties
B58: =QuantityTakeoff!Y75 -> 0
B59: 0
B60: 0
A61: Total | B61: =SUBTOTAL(9,B58:B60) -> 0
A62: Division 11 Equipment
B63: 0
B64: 0
B65: 0
B66: 0
A67: Total | B67: =SUBTOTAL(9,B63:B66) -> 0
A68: Division 12 Furnishings
B69: =QuantityTakeoff!Y79 -> 0
B70: 0
A71: Total | B71: =SUBTOTAL(9,B69:B70) -> 0
A72: Division 21 Fire Suppression
B73: =QuantityTakeoff!Y80 -> 23500
B74: 0
A75: Total | B75: =SUBTOTAL(9,B73:B74) -> 23500
A76: Division 22 Plumbing
B77: =QuantityTakeoff!Y82 -> 92500
B78: 0
A79: Total | B79: =ROUNDUP(SUBTOTAL(9,B77),0) -> 92500
A80: Division 23 HVAC | H80: =B83-530000 -> 943000
B81: =QuantityTakeoff!Y87 -> 1473000
B82: 0
A83: Total | B83: =SUBTOTAL(9,B81) -> 1473000
A84: Division 26 Electrical
B85: =QuantityTakeoff!Y93 -> 863000
B86: 0
A87: Total | B87: =SUBTOTAL(9,B85) -> 863000 | E87: =QuantityTakeoff!Y107 -> 0
A88: Division 27 Communications
A91: Total | B91: =SUBTOTAL(9,B89) -> 0
A92: Division 28 Electronic Safety and Secutiry
B93: =QuantityTakeoff!Y111 -> 0
A95: Total | B95: =SUBTOTAL(9,B93:B94) -> 0
A96: Division 31 Earthwork
B97: =QuantityTakeoff!Y113 -> 0
B98: 0
B99: 0
B100: 0
B101: 0
A102: Total | B102: =SUBTOTAL(9,B97:B101) -> 0
A103: Division 31.10 Soil Stabilization
A106: Total | B106: =SUBTOTAL(9,B104:B105) -> 0
A107: Division 32 Exterior Improvements
B108: =QuantityTakeoff!Y123 -> 0
B109: 0
...

Sheet General Conditions
B1: Project Duration | C1: 3 | D1: Months | E1: 12 | F1: Weeks
A3: General Conditions | E3: Quantity | F3: Unit | G3: Rate
A4: 3128 | B4: Project Manager | C4: =E4*G4 -> 45552 | E4: 12 | F4: Weeks | G4: 3796
A5: 3144 | B5: Superintendent | C5: =E5*G5 -> 40500 | E5: 12 | F5: Weeks | G5: 3375
A6: 3129 | B6: PM Fuel | C6: =E6*G6 -> 1200 | E6: 12 | F6: Weeks | G6: 100
A7: 3130 | B7: PM Truck | C7: =E7*G7 -> 3300 | E7: 6 | F7: Months | G7: 550
A8: 3245 | B8: Office Supplies | C8: =E8*G8 -> 450 | E8: 3 | F8: Months | G8: 150
A9: 3247 | B9: Printing & Copying | C9: =E9*G9 -> 2250 | E9: 3 | F9: LS | G9: 750
A10: 3329 | B10: Leed Documentation | C10: =E10*G10 -> 0 | E10: 0 | F10: LS
A11: 4126 | B11: Permit Requirements | C11: =E11*G11 -> 15000 | E11: 1 | F11: LS | G11: 15000
A12: 4523 | B12: Testing & Inspections | C12: =E12*G12 -> 3500 | E12: 1 | F12: LS | G12: 3500
A13: 5113 | B13: Temporary Electric | C13: =E13*G13 -> 0 | E13: 0 | F13: Months | G13: 1000
A14: 5216 | B14: First Aid/Safety Supplies | C14: =E14*G14 -> 0 | E14: 0 | F14: Months | G14: 75
A15: 5213 | B15: Field Office | C15: =E15*G15 -> 0 | E15: 0 | F15: Months | G15: 650
A16: 5217 | B16: Safety Inspections | C16: =E16*G16 -> 0 | E16: 0 | F16: Months | G16: 150
A17: 5219 | B17: Temp Toilets | C17: =E17*G17 -> 0 | E17: 0 | F17: Months | G17: 350
A18: 6113 | B18: Software Licensing | C18: =E18*G18 -> 1500 | E18: 1 | F18: LS | G18: 1500
A19: 6500 | B19: Travel & Entertaintment | C19: =E19*G19 -> 36000 | E19: 3 | F19: Months | G19: 12000
A20: 7333 | B20: Misc Small Tools | C20: =E20*G20 -> 0 | E20: 0 | F20: Months | G20: 500
A21: 7336 | B21: Equipment Rental | C21: =E21*G21 -> 3750 | E21: 5 | F21: Months | G21: 750
A22: 7413 | B22: Progress Cleaning | C22: =E22*G22 -> 3250 | E22: 5 | F22: Months | G22: 650
A23: 7419 | B23: Dumpsters | C23: =E23*G23 -> 4500 | E23: 6 | F23: EA | G23: 750
B24: Temp Fencing | C24: =E24*G24 -> 0 | E24: 0 | F24: lf | G24: 10
A25: 7423 | B25: Final Cleaning | C25: =E25*G25 -> 2500 | E25: 5000 | F25: SF | G25: 0.5
A27: Total | C27: =ROUNDUP(SUM(C4:C25),0) -> 163252

Sheet QuantityTakeoff
A2: Client: | C2: Ulta Beauty | F2: Job Name: | H2: Ulta Fresno New RTUs R1 | M2: Estimate Number:
A3: Location: | C3: Fresno, California | F3: Estimate Date: | H3: 45501
A4: Estimator: | C4: AJ Taylor | F4: Revision Date: | H4: 45875
D6: Dimensions | J6: Material | M6: Labor | Q6: Equipment (incl fuel) | U6: Subcontract
A7: Line | B7: Division | C7: Description | D7: Length | E7: Width | F7: Depth | G7: No. of Ea. | H7: Quantity | I7: Unit | J7: Unit Price | K7: Cost | L7: Crew | M7: Hrs | N7: MH | O7: Rate | P7: Cost | Q7: Duration | R7: Unit | S7: Rate | T7: Cost | U7: Unit Price | V7: Cost | W7: Total Cost | X7: Comments
A8: 1 | B8: 00 Design | K8: =J8*H8 -> 0 | N8: =ROUND(L8*M8*H8,0) -> 0 | P8: =O8*N8 -> 0 | T8: =S8*Q8 -> 0 | V8: =H8*U8 -> 0 | W8: =V8+T8+P8+K8 -> 0 | Y8: =SUM(W8:W16) -> 0
A9: =A8+1 -> 2 | C9: Alleato Coordination | H9: 0 | I9: lot | K9: =J9*H9 -> 0 | N9: =ROUND(L9*M9*H9,0) -> 0 | P9: =O9*N9 -> 0 | T9: =S9*Q9 -> 0 | U9: 7000 | V9: =H9*U9 -> 0 | W9: =V9+T9+P9+K9 -> 0
A10: =A9+1 -> 3 | C10: Boundary Survey | H10: 0 | I10: lot | K10: =J10*H10 -> 0 | N10: =ROUND(L10*M10*H10,0) -> 0 | P10: =O10*N10 -> 0 | T10: =S10*Q10 -> 0 | U10: 0 | V10: =H10*U10 -> 0 | W10: =V10+T10+P10+K10 -> 0
A11: =A10+1 -> 4 | C11: Topographic Survey | H11: 0 | I11: lot | K11: =J11*H11 -> 0 | N11: =ROUND(L11*M11*H11,0) -> 0 | P11: =O11*N11 -> 0 | T11: =S11*Q11 -> 0 | U11: 0 | V11: =H11*U11 -> 0 | W11: =V11+T11+P11+K11 -> 0
A12: =A11+1 -> 5 | C12: Geotechnical Survey | H12: 0 | I12: lot | K12: =J12*H12 -> 0 | N12: =ROUND(L12*M12*H12,0) -> 0 | P12: =O12*N12 -> 0 | T12: =S12*Q12 -> 0 | U12: 0 | V12: =H12*U12 -> 0 | W12: =V12+T12+P12+K12 -> 0
A13: =A12+1 -> 6 | C13: Civil Design | H13: 0 | I13: lot | K13: =J13*H13 -> 0 | N13: =ROUND(L13*M13*H13,0) -> 0 | P13: =O13*N13 -> 0 | T13: =S13*Q13 -> 0 | U13: 0 | V13: =H13*U13 -> 0 | W13: =V13+T13+P13+K13 -> 0
A14: =A13+1 -> 7 | C14: Architectural Design | H14: 0 | I14: lot | K14: =J14*H14 -> 0 | N14: =ROUND(L14*M14*H14,0) -> 0 | P14: =O14*N14 -> 0 | T14: =S14*Q14 -> 0 | U14: 5000 | V14: =H14*U14 -> 0 | W14: =V14+T14+P14+K14 -> 0
A15: =A14+1 -> 8 | C15: Structural | H15: 0 | I15: lot | K15: =J15*H15 -> 0 | N15: =ROUND(L15*M15*H15,0) -> 0 | P15: =O15*N15 -> 0 | T15: =S15*Q15 -> 0 | U15: 5000 | V15: =H15*U15 -> 0 | W15: =V15+T15+P15+K15 -> 0
A16: =A15+1 -> 9 | C16: MEP Design | H16: 0 | I16: lot | K16: =J16*H16 -> 0 | N16: =ROUND(L16*M16*H16,0) -> 0 | P16: =O16*N16 -> 0 | T16: =S16*Q16 -> 0 | U16: 1000 | V16: =H16*U16 -> 0 | W16: =V16+T16+P16+K16 -> 0
A17: =A16+1 -> 10 | B17: 01 General Conditions | K17: =J17*H17 -> 0 | N17: =ROUND(L17*M17*H17,0) -> 0 | P17: =O17*N17 -> 0 | T17: =S17*Q17 -> 0 | V17: =H17*U17 -> 0 | W17: =V17+T17+P17+K17 -> 0 | Y17: =SUM(W17:W22) -> 0
A18: =A17+1 -> 11 | C18: Application Fees | H18: 0 | I18: lot | K18: =J18*H18 -> 0 | N18: =ROUND(L18*M18*H18,0) -> 0 | P18: =O18*N18 -> 0 | T18: =S18*Q18 -> 0 | U18: 4000 | V18: =H18*U18 -> 0 | W18: =V18+T18+P18+K18 -> 0
A19: =A18+1 -> 12 | C19: State Release ($150 + $.05 x floor sq footage) | I19: lot | K19: =J19*H19 -> 0 | N19: =ROUND(L19*M19*H19,0) -> 0 | P19: =O19*N19 -> 0 | T19: =S19*Q19 -> 0 | U19: 0 | V19: =H19*U19 -> 0 | W19: =V19+T19+P19+K19 -> 0
A20: =A19+1 -> 13 | C20: Local Permits | H20: 0 | I20: lot | K20: =J20*H20 -> 0 | N20: =ROUND(L20*M20*H20,0) -> 0 | P20: =O20*N20 -> 0 | T20: =S20*Q20 -> 0 | U20: 4000 | V20: =H20*U20 -> 0 | W20: =V20+T20+P20+K20 -> 0
A21: =A20+1 -> 14 | C21: Local Planning | H21: 0 | I21: lot | K21: =J21*H21 -> 0 | N21: =ROUND(L21*M21*H21,0) -> 0 | P21: =O21*N21 -> 0 | T21: =S21*Q21 -> 0 | U21: 4000 | V21: =H21*U21 -> 0 | W21: =V21+T21+P21+K21 -> 0
A22: =A21+1 -> 15 | K22: =J22*H22 -> 0 | N22: =ROUND(L22*M22*H22,0) -> 0 | P22: =O22*N22 -> 0 | T22: =S22*Q22 -> 0 | V22: =H22*U22 -> 0 | W22: =V22+T22+P22+K22 -> 0
A23: =A22+1 -> 16 | B23: 02 Existing Conditions | K23: =J23*H23 -> 0 | N23: =ROUND(L23*M23*H23,0) -> 0 | P23: =O23*N23 -> 0 | T23: =S23*Q23 -> 0 | V23: =H23*U23 -> 0 | W23: =V23+T23+P23+K23 -> 0 | Y23: =SUM(W23:W25) -> 0
A24: =A23+1 -> 17 | H24: 0 | I24: lot | K24: =J24*H24 -> 0 | L24: 1 | M24: 4 | N24: =ROUND(L24*M24*H24,0) -> 0 | O24: 50 | P24: =O24*N24 -> 0 | T24: =S24*Q24 -> 0 | U24: 0 | V24: =H24*U24 -> 0 | W24: =V24+T24+P24+K24 -> 0
A25: =A24+1 -> 18 | H25: 0 | I25: lot | K25: =J25*H25 -> 0 | N25: =ROUND(L25*M25*H25,0) -> 0 | P25: =O25*N25 -> 0 | T25: =S25*Q25 -> 0 | U25: 0 | V25: =H25*U25 -> 0 | W25: =V25+T25+P25+K25 -> 0 | X25: SWAG
A26: =A25+1 -> 19 | B26: 03 Concrete | K26: =J26*H26 -> 0 | N26: =ROUND(L26*M26*H26,0) -> 0 | P26: =O26*N26 -> 0 | T26: =S26*Q26 -> 0 | V26: =H26*U26 -> 0 | W26: =V26+T26+P26+K26 -> 0 | Y26: =SUM(W26:W32) -> 0
A27: =A26+1 -> 20 | C27: Transformer Pads | I27: EA | K27: =J27*H27 -> 0 | N27: =ROUND(L27*M27*H27,0) -> 0 | P27: =O27*N27 -> 0 | T27: =S27*Q27 -> 0 | U27: 2500 | V27: =H27*U27 -> 0 | W27: =V27+T27+P27+K27 -> 0 | X27: Included in Mid South
A28: =A27+1 -> 21 | C28: Generator Pads | I28: EA | K28: =J28*H28 -> 0 | N28: =ROUND(L28*M28*H28,0) -> 0 | P28: =O28*N28 -> 0 | T28: =S28*Q28 -> 0 | U28: 5000 | V28: =H28*U28 -> 0 | W28: =V28+T28+P28+K28 -> 0 | X28: Included in Mid South | Y28: internal cont. | Z28: 18300
A29: =A28+1 -> 22 | C29: Bollard Concrete | I29: EA | K29: =J29*H29 -> 0 | N29: =ROUND(L29*M29*H29,0) -> 0 | P29: =O29*N29 -> 0 | T29: =S29*Q29 -> 0 | U29: 200 | V29: =H29*U29 -> 0 | W29: =V29+T29+P29+K29 -> 0 | X29: Included in Mid South
A30: =A29+1 -> 23 | C30: Rebar | I30: LS | K30: =J30*H30 -> 0 | N30: =ROUND(L30*M30*H30,0) -> 0 | P30: =O30*N30 -> 0 | T30: =S30*Q30 -> 0 | U30: 1050 | V30: =H30*U30 -> 0 | W30: =V30+T30+P30+K30 -> 0 | X30: Included in Mid South
A31: =A30+1 -> 24 | C31: Concrete Subcontractor Include stoop at door | I31: lot | K31: =J31*H31 -> 0 | N31: =ROUND(L31*M31*H31,0) -> 0 | P31: =O31*N31 -> 0 | T31: =S31*Q31 -> 0 | U31: 20000 | V31: =H31*U31 -> 0 | W31: =V31+T31+P31+K31 -> 0 | X31: Plug Number
A32: =A31+1 -> 25 | H32: 0 | I32: lot | K32: =J32*H32 -> 0 | N32: =ROUND(L32*M32*H32,0) -> 0 | P32: =O32*N32 -> 0 | T32: =S32*Q32 -> 0 | U32: 0 | V32: =H32*U32 -> 0 | W32: =V32+T32+P32+K32 -> 0
A33: =A32+1 -> 26 | B33: 04 Masonry | K33: =J33*H33 -> 0 | N33: =ROUND(L33*M33*H33,0) -> 0 | P33: =O33*N33 -> 0 | T33: =S33*Q33 -> 0 | V33: =H33*U33 -> 0 | W33: =V33+T33+P33+K33 -> 0 | Y33: =SUM(W33:W35) -> 0
A34: =A33+1 -> 27 | I34: sf | K34: =J34*H34 -> 0 | N34: =ROUND(L34*M34*H34,0) -> 0 | P34: =O34*N34 -> 0 | T34: =S34*Q34 -> 0 | V34: =H34*U34 -> 0 | W34: =V34+T34+P34+K34 -> 0
A35: =A34+1 -> 28 | I35: lf | K35: =J35*H35 -> 0 | N35: =ROUND(L35*M35*H35,0) -> 0 | P35: =O35*N35 -> 0 | T35: =S35*Q35 -> 0 | V35: =H35*U35 -> 0 | W35: =V35+T35+P35+K35 -> 0
A36: =A35+1 -> 29 | B36: 05 Metals | K36: =J36*H36 -> 0 | N36: =ROUND(L36*M36*H36,0) -> 0 | P36: =O36*N36 -> 0 | T36: =S36*Q36 -> 0 | V36: =H36*U36 -> 0 | W36: =V36+T36+P36+K36 -> 0 | Y36: =SUM(W36:W40) -> 247500
A37: =A36+1 -> 30 | K37: =J37*H37 -> 0 | N37: =ROUND(L37*M37*H37,0) -> 0 | P37: =O37*N37 -> 0 | T37: =S37*Q37 -> 0 | V37: =H37*U37 -> 0 | W37: =V37+T37+P37+K37 -> 0
A38: =A37+1 -> 31 | C38: Reinforce Joists 8 AANON Units reuse spaces | H38: 45 | I38: ea | K38: =J38*H38 -> 0 | N38: =ROUND(L38*M38*H38,0) -> 0 | P38: =O38*N38 -> 0 | T38: =S38*Q38 -> 0 | U38: 4500 | V38: =H38*U38 -> 202500 | W38: =V38+T38+P38+K38 -> 202500
A39: =A38+1 -> 32 | C39: internal cont. | H39: 1 | I39: lot | K39: =J39*H39 -> 0 | N39: =ROUND(L39*M39*H39,0) -> 0 | P39: =O39*N39 -> 0 | T39: =S39*Q39 -> 0 | U39: 25000 | V39: =H39*U39 -> 25000 | W39: =V39+T39+P39+K39 -> 25000 | X39: Allowance
A40: =A39+1 -> 33 | C40: Design | H40: 1 | I40: lot | K40: =J40*H40 -> 0 | N40: =ROUND(L40*M40*H40,0) -> 0 | P40: =O40*N40 -> 0 | T40: =S40*Q40 -> 0 | U40: 20000 | V40: =H40*U40 -> 20000 | W40: =V40+T40+P40+K40 -> 20000
A41: =A40+1 -> 34 | B41: 06 Wood Plastics Composits | K41: =J41*H41 -> 0 | N41: =ROUND(L41*M41*H41,0) -> 0 | P41: =O41*N41 -> 0 | T41: =S41*Q41 -> 0 | V41: =H41*U41 -> 0 | W41: =V41+T41+P41+K41 -> 0 | Y41: =SUM(W41:W48) -> 0
A42: =A41+1 -> 35 | C42: Hardi Board | H42: 0 | I42: lot | K42: =J42*H42 -> 0 | N42: =ROUND(L42*M42*H42,0) -> 0 | P42: =O42*N42 -> 0 | T42: =S42*Q42 -> 0 | U42: 0 | V42: =H42*U42 -> 0 | W42: =V42+T42+P42+K42 -> 0
A43: =A42+1 -> 36 | C43: Exterior Plywood/Blocking | H43: 0 | I43: lot | K43: =J43*H43 -> 0 | N43: =ROUND(L43*M43*H43,0) -> 0 | P43: =O43*N43 -> 0 | T43: =S43*Q43 -> 0 | U43: 0 | V43: =H43*U43 -> 0 | W43: =V43+T43+P43+K43 -> 0
A44: =A43+1 -> 37 | C44: Bar Support Wall | H44: 0 | I44: lot | K44: =J44*H44 -> 0 | N44: =ROUND(L44*M44*H44,0) -> 0 | P44: =O44*N44 -> 0 | T44: =S44*Q44 -> 0 | U44: 0 | V44: =H44*U44 -> 0 | W44: =V44+T44+P44+K44 -> 0
A45: =A44+1 -> 38 | C45: Wood Bar Top | H45: 0 | I45: lot | J45: 0 | K45: =J45*H45 -> 0 | N45: =ROUND(L45*M45*H45,0) -> 0 | P45: =O45*N45 -> 0 | T45: =S45*Q45 -> 0 | U45: 0 | V45: =H45*U45 -> 0 | W45: =V45+T45+P45+K45 -> 0
A46: =A45+1 -> 39 | C46: Solid Surface Bar Top | H46: 0 | I46: lot | K46: =J46*H46 -> 0 | N46: =ROUND(L46*M46*H46,0) -> 0 | P46: =O46*N46 -> 0 | T46: =S46*Q46 -> 0 | U46: 0 | V46: =H46*U46 -> 0 | W46: =V46+T46+P46+K46 -> 0
A47: =A46+1 -> 40 | C47: Delivery | H47: 0 | I47: lot | K47: =J47*H47 -> 0 | N47: =ROUND(L47*M47*H47,0) -> 0 | P47: =O47*N47 -> 0 | T47: =S47*Q47 -> 0 | U47: 0 | V47: =H47*U47 -> 0 | W47: =V47+T47+P47+K47 -> 0
A48: =A47+1 -> 41 | C48: Interior Wall Framing | H48: 0 | I48: LF | J48: 0 | K48: =J48*H48 -> 0 | N48: =ROUND(L48*M48*H48,0) -> 0 | P48: =O48*N48 -> 0 | T48: =S48*Q48 -> 0 | U48: 0 | V48: =H48*U48 -> 0 | W48: =V48+T48+P48+K48 -> 0
A49: =A48+1 -> 42 | B49: 07 Thermal and Moisture Protection | K49: =J49*H49 -> 0 | N49: =ROUND(L49*M49*H49,0) -> 0 | P49: =O49*N49 -> 0 | T49: =S49*Q49 -> 0 | V49: =H49*U49 -> 0 | W49: =V49+T49+P49+K49 -> 0 | Y49: =SUM(W49:W59) -> 72000
A50: =A49+1 -> 43 | I50: sf | K50: =J50*H50 -> 0 | N50: =ROUND(L50*M50*H50,0) -> 0 | P50: =O50*N50 -> 0 | T50: =S50*Q50 -> 0 | U50: 0 | V50: =H50*U50 -> 0 | W50: =V50+T50+P50+K50 -> 0
A51: =A50+1 -> 44 | C51: roofing for curbs | H51: 12 | I51: ea | K51: =J51*H51 -> 0 | N51: =ROUND(L51*M51*H51,0) -> 0 | P51: =O51*N51 -> 0 | T51: =S51*Q51 -> 0 | U51: 6000 | V51: =H51*U51 -> 72000 | W51: =V51+T51+P51+K51 -> 72000 | X51: SWAG
A52: =A51+1 -> 45 | P52: =O52*N52 -> 0 | T52: =S52*Q52 -> 0 | U52: 0 | V52: =H52*U52 -> 0 | W52: =V52+T52+P52+K52 -> 0
A53: =A52+1 -> 46 | C53: Roofing at Curbs | H53: 0 | I53: ea | P53: =O53*N53 -> 0 | T53: =S53*Q53 -> 0 | U53: 1792 | V53: =H53*U53 -> 0 | W53: =V53+T53+P53+K53 -> 0 | X53: All State Roofing
A54: =A53+1 -> 47 | P54: =O54*N54 -> 0 | T54: =S54*Q54 -> 0 | U54: 0 | V54: =H54*U54 -> 0 | W54: =V54+T54+P54+K54 -> 0
A55: =A54+1 -> 48 | P55: =O55*N55 -> 0 | T55: =S55*Q55 -> 0 | U55: 0 | V55: =H55*U55 -> 0 | W55: =V55+T55+P55+K55 -> 0
A56: =A55+1 -> 49 | P56: =O56*N56 -> 0 | T56: =S56*Q56 -> 0 | U56: 0 | V56: =H56*U56 -> 0 | W56: =V56+T56+P56+K56 -> 0
A57: =A56+1 -> 50 | P57: =O57*N57 -> 0 | T57: =S57*Q57 -> 0 | U57: 0 | V57: =H57*U57 -> 0 | W57: =V57+T57+P57+K57 -> 0
A58: =A57+1 -> 51 | P58: =O58*N58 -> 0 | T58: =S58*Q58 -> 0 | U58: 0 | V58: =H58*U58 -> 0 | W58: =V58+T58+P58+K58 -> 0
A59: =A58+1 -> 52 | P59: =O59*N59 -> 0 | T59: =S59*Q59 -> 0 | U59: 0 | V59: =H59*U59 -> 0 | W59: =V59+T59+P59+K59 -> 0
A60: =A59+1 -> 53 | B60: 08 Openings | K60: =J60*H60 -> 0 | N60: =ROUND(L60*M60*H60,0) -> 0 | P60: =O60*N60 -> 0 | T60: =S60*Q60 -> 0 | V60: =H60*U60 -> 0 | W60: =V60+T60+P60+K60 -> 0 | Y60: =SUM(W60:W66) -> 0
A61: =A60+1 -> 54 | C61: cut opening for new egress | I61: ea | K61: =J61*H61 -> 0 | N61: =ROUND(L61*M61*H61,0) -> 0 | P61: =O61*N61 -> 0 | T61: =S61*Q61 -> 0 | U61: 3000 | V61: =H61*U61 -> 0 | W61: =V61+T61+P61+K61 -> 0 | X61: Plug Number
A62: =A61+1 -> 55 | C62: install exterior door | I62: ea | J62: 2500 | K62: =J62*H62 -> 0 | N62: =ROUND(L62*M62*H62,0) -> 0 | P62: =O62*N62 -> 0 | T62: =S62*Q62 -> 0 | U62: =1*8*100 -> 800 | V62: =H62*U62 -> 0 | W62: =V62+T62+P62+K62 -> 0 | X62: Plug Number
A63: =A62+1 -> 56 | C63: concrete stoop | I63: lot | K63: =J63*H63 -> 0 | N63: =ROUND(L63*M63*H63,0) -> 0 | P63: =O63*N63 -> 0 | T63: =S63*Q63 -> 0 | U63: 2000 | V63: =H63*U63 -> 0 | W63: =V63+T63+P63+K63 -> 0 | X63: Plug Number
A64: =A63+1 -> 57 | C64: wall pack for egress lighting | I64: ea | K64: =J64*H64 -> 0 | N64: =ROUND(L64*M64*H64,0) -> 0 | P64: =O64*N64 -> 0 | T64: =S64*Q64 -> 0 | U64: 1000 | V64: =H64*U64 -> 0 | W64: =V64+T64+P64+K64 -> 0 | X64: Plug Number
A65: =A64+1 -> 58 | C65: gate at north fence | I65: ea | J65: 0 | K65: =J65*H65 -> 0 | M65: 2.5 | N65: =ROUND(L65*M65*H65,0) -> 0 | O65: 65 | P65: =O65*N65 -> 0 | T65: =S65*Q65 -> 0 | U65: 5000 | V65: =H65*U65 -> 0 | W65: =V65+T65+P65+K65 -> 0 | X65: Plug Number
A66: =A65+1 -> 59 | C66: misc, paint caulk | I66: ea | J66: 0 | K66: =J66*H66 -> 0 | M66: 2.5 | N66: =ROUND(L66*M66*H66,0) -> 0 | O66: 65 | P66: =O66*N66 -> 0 | T66: =S66*Q66 -> 0 | U66: 1000 | V66: =H66*U66 -> 0 | W66: =V66+T66+P66+K66 -> 0 | X66: Plug Number
A67: =A66+1 -> 60 | B67: 09 Finishes | K67: =J67*H67 -> 0 | N67: =L67*M67*H67 -> 0 | P67: =O67*N67 -> 0 | T67: =S67*Q67 -> 0 | V67: =H67*U67 -> 0 | W67: =V67+T67+P67+K67 -> 0 | Y67: =SUM(W67:W74) -> 0 | AA67: height of wall: | AB67: 12
A68: =A67+1 -> 61 | C68: internal cont | I68: lot | J68: 0 | K68: =J68*H68 -> 0 | L68: 0 | M68: 0.005 | N68: =L68*M68*H68 -> 0 | O68: 75 | P68: =O68*N68 -> 0 | T68: =S68*Q68 -> 0 | U68: 190141 | V68: =H68*U68 -> 0 | W68: =V68+T68+P68+K68 -> 0 | AA68: 6" 20' | AB68: 20.9 | AC68: =(#REF!*1.15) -> #REF! | AD68: =AB68*AC68 -> #REF!
A69: =A68+1 -> 62 | C69: Design? | H69: 0 | I69: ea | K69: =J69*H69 -> 0 | N69: =L69*M69*H69 -> 0 | P69: =O69*N69 -> 0 | T69: =S69*Q69 -> 0 | U69: 0 | V69: =H69*U69 -> 0 | W69: =V69+T69+P69+K69 -> 0 | Y69: internal cont. | AA69: 4x12 Type X | AB69: 0.51 | AC69: =((#REF!*AB67*2)+(#REF!*AB67)+(200*10))*1.1 -> #REF! | AD69: =AB69*AC69 -> #REF!
A70: =A69+1 -> 63 | C70: Paint Walls | H70: 0 | I70: ea | K70: =J70*H70 -> 0 | N70: =L70*M70*H70 -> 0 | P70: =O70*N70 -> 0 | T70: =S70*Q70 -> 0 | U70: 0 | V70: =H70*U70 -> 0 | W70: =V70+T70+P70+K70 -> 0 | AA70: Nails/Screws | AB70: 500 | AC70: 1 | AD70: =AB70*AC70 -> 500
A71: =A70+1 -> 64 | C71: Patch Flooring | H71: 0 | I71: EA | K71: =J71*H71 -> 0 | N71: =L71*M71*H71 -> 0 | P71: =O71*N71 -> 0 | T71: =S71*Q71 -> 0 | U71: 0 | V71: =H71*U71 -> 0 | W71: =V71+T71+P71+K71 -> 0
A72: =A71+1 -> 65 | C72: insulation on drop ceiling | H72: 0 | I72: sf | K72: =J72*H72 -> 0 | N72: =L72*M72*H72 -> 0 | P72: =O72*N72 -> 0 | T72: =S72*Q72 -> 0 | U72: 0 | V72: =H72*U72 -> 0 | W72: =V72+T72+P72+K72 -> 0 | X72: Included with Eubanks
A73: =A72+1 -> 66 | C73: Aluminum Cap grid with USG 2410 tile and insulation | G73: 14000 | I73: lot | K73: =J73*H73 -> 0 | N73: =ROUND(L73*M73*H73,0) -> 0 | P73: =O73*N73 -> 0 | T73: =S73*Q73 -> 0 | U73: 859859 | V73: =H73*U73 -> 0 | W73: =V73+T73+P73+K73 -> 0 | X73: 859859 Eubanks
A74: =A73+1 -> 67 | C74: Add for Seismic | I74: lot | K74: =J74*H74 -> 0 | N74: =ROUND(L74*M74*H74,0) -> 0 | P74: =O74*N74 -> 0 | T74: =S74*Q74 -> 0 | U74: 0 | V74: =H74*U74 -> 0 | W74: =V74+T74+P74+K74 -> 0
A75: =A74+1 -> 68 | B75: 10 Specialties | K75: =J75*H75 -> 0 | N75: =L75*M75*H75 -> 0 | P75: =O75*N75 -> 0 | T75: =S75*Q75 -> 0 | V75: =H75*U75 -> 0 | W75: =V75+T75+P75+K75 -> 0 | Y75: =SUM(W75:W76) -> 0
A76: =A75+1 -> 69 | G76: 0 | H76: 1 | I76: ea | K76: =J76*H76 -> 0 | N76: =L76*M76*H76 -> 0 | P76: =O76*N76 -> 0 | T76: =S76*Q76 -> 0 | U76: 0 | V76: =H76*U76 -> 0 | W76: =V76+T76+P76+K76 -> 0
A77: =A76+1 -> 70 | B77: 11 Equipment | K77: =J77*H77 -> 0 | N77: =L77*M77*H77 -> 0 | P77: =O77*N77 -> 0 | T77: =S77*Q77 -> 0 | V77: =H77*U77 -> 0 | W77: =V77+T77+P77+K77 -> 0
A78: =A77+1 -> 71 | C78: by owner | K78: =J78*H78 -> 0 | N78: =L78*M78*H78 -> 0 | P78: =O78*N78 -> 0 | T78: =S78*Q78 -> 0 | V78: =H78*U78 -> 0 | W78: =V78+T78+P78+K78 -> 0
A79: =A78+1 -> 72 | B79: 12 Furnishings | K79: =J79*H79 -> 0 | N79: =L79*M79*H79 -> 0 | P79: =O79*N79 -> 0 | T79: =S79*Q79 -> 0 | V79: =H79*U79 -> 0 | W79: =V79+T79+P79+K79 -> 0 | Y79: =SUM(W79:W79) -> 0
A80: =A79+1 -> 73 | B80: 21 Fire Suppression | K80: =J80*H80 -> 0 | N80: =L80*M80*H80 -> 0 | P80: =O80*N80 -> 0 | T80: =S80*Q80 -> 0 | V80: =H80*U80 -> 0 | W80: =V80+T80+P80+K80 -> 0 | Y80: =SUM(W80:W81) -> 23500
A81: =A80+1 -> 74 | C81: Fire Supression Allowance | H81: 1 | I81: ea | K81: =J81*H81 -> 0 | N81: =L81*M81*H81 -> 0 | P81: =O81*N81 -> 0 | T81: =S81*Q81 -> 0 | U81: 23500 | V81: =H81*U81 -> 23500 | W81: =V81+T81+P81+K81 -> 23500 | X81: Plug Number
A82: =A81+1 -> 75 | B82: 22 Plumbing | I82: lot | K82: =J82*H82 -> 0 | N82: =L82*M82*H82 -> 0 | P82: =O82*N82 -> 0 | T82: =S82*Q82 -> 0 | V82: =H82*U82 -> 0 | W82: =V82+T82+P82+K82 -> 0 | Y82: =SUM(W82:W86) -> 92500
A83: =A82+1 -> 76 | C83: Condensate Drains | H83: 0 | I83: lot | K83: =J83*H83 -> 0 | N83: =L83*M83*H83 -> 0 | P83: =O83*N83 -> 0 | T83: =S83*Q83 -> 0 | U83: 275000 | V83: =H83*U83 -> 0 | W83: =V83+T83+P83+K83 -> 0 | X83: Valley Air
A84: =A83+1 -> 77 | C84: gas for rtus | H84: 5 | I84: ea | K84: =J84*H84 -> 0 | N84: =L84*M84*H84 -> 0 | P84: =O84*N84 -> 0 | T84: =S84*Q84 -> 0 | U84: 7500 | V84: =H84*U84 -> 37500 | W84: =V84+T84+P84+K84 -> 37500 | X84: Plug Number
A85: =A84+1 -> 78 | C85: internal cont | H85: 1 | I85: lot | K85: =J85*H85 -> 0 | N85: =L85*M85*H85 -> 0 | P85: =O85*N85 -> 0 | T85: =S85*Q85 -> 0 | U85: 35000 | V85: =H85*U85 -> 35000 | W85: =V85+T85+P85+K85 -> 35000 | X85: Plug Number
A86: =A85+1 -> 79 | C86: Design | H86: 1 | I86: ea | K86: =J86*H86 -> 0 | N86: =L86*M86*H86 -> 0 | P86: =O86*N86 -> 0 | T86: =S86*Q86 -> 0 | U86: 20000 | V86: =H86*U86 -> 20000 | W86: =V86+T86+P86+K86 -> 20000 | X86: Plug Number
A87: =A86+1 -> 80 | B87: 23 HVAC | I87: lot | K87: =J87*H87 -> 0 | N87: =L87*M87*H87 -> 0 | P87: =O87*N87 -> 0 | T87: =S87*Q87 -> 0 | V87: =H87*U87 -> 0 | W87: =V87+T87+P87+K87 -> 0 | Y87: =SUM(W87:W92) -> 1473000
A88: =A87+1 -> 81 | C88: (7) 25 ton units | H88: 1 | I88: lot | K88: =J88*H88 -> 0 | N88: =L88*M88*H88 -> 0 | P88: =O88*N88 -> 0 | T88: =S88*Q88 -> 0 | U88: 832000 | V88: =H88*U88 -> 832000 | W88: =V88+T88+P88+K88 -> 832000 | X88: ACCO
A89: =A88+1 -> 82 | C89: HVLS Fans | H89: 4 | I89: lot | K89: =J89*H89 -> 0 | N89: =L89*M89*H89 -> 0 | P89: =O89*N89 -> 0 | U89: 25000 | V89: =H89*U89 -> 100000 | W89: =V89+T89+P89+K89 -> 100000 | X89: ACCO
A90: =A89+1 -> 83 | C90: structural curbs | H90: 0 | I90: ea | K90: =J90*H90 -> 0 | N90: =ROUND(L90*M90*H90,0) -> 0 | P90: =O90*N90 -> 0 | U90: 15000 | V90: =H90*U90 -> 0 | W90: =V90+T90+P90+K90 -> 0
A91: =A90+1 -> 84 | C91: internal cont. | H91: 1 | I91: lot | K91: =J91*H91 -> 0 | N91: =ROUND(L91*M91*H91,0) -> 0 | P91: =O91*N91 -> 0 | U91: 500000 | V91: =H91*U91 -> 500000 | W91: =V91+T91+P91+K91 -> 500000 | X91: Internal cont.
A92: =A90+1 -> 84 | C92: Design | H92: 1 | I92: ea | K92: =J92*H92 -> 0 | N92: =ROUND(L92*M92*H92,0) -> 0 | P92: =O92*N92 -> 0 | T92: =S92*Q92 -> 0 | U92: 41000 | V92: =H92*U92 -> 41000 | W92: =V92+T92+P92+K92 -> 41000 | X92: ACCO
A93: =A89+1 -> 83 | B93: 26 Electrical | I93: lot | P93: =O93*N93 -> 0 | T93: =S93*Q93 -> 0 | U93: 0 | V93: =H93*U93 -> 0 | W93: =V93+T93+P93+K93 -> 0 | Y93: =SUM(W93:W108) -> 863000
A94: =A93+1 -> 84 | C94: Fire Alarm | H94: 1 | I94: lot | K94: =J94*H94 -> 0 | N94: =ROUND(L94*M94*H94,0) -> 0 | P94: =O94*N94 -> 0 | T94: =S94*Q94 -> 0 | U94: 63000 | V94: =H94*U94 -> 63000 | W94: =V94+T94+P94+K94 -> 63000
A95: =A94+1 -> 85 | C95: Electrical sub | H95: 1 | I95: lot | K95: =J95*H95 -> 0 | N95: =ROUND(L95*M95*H95,0) -> 0 | P95: =O95*N95 -> 0 | T95: =S95*Q95 -> 0 | U95: 800000 | V95: =H95*U95 -> 800000 | W95: =V95+T95+P95+K95 -> 800000 | X95: Plug Number
A96: =A95+1 -> 86 | C96: 800 Amp Service from existing Circuit - 28 containers | I96: ea | K96: =J96*H96 -> 0 | N96: =ROUND(L96*M96*H96,0) -> 0 | P96: =O96*N96 -> 0 | T96: =S96*Q96 -> 0 | U96: 0 | V96: =H96*U96 -> 0 | W96: =V96+T96+P96+K96 -> 0
A97: =A96+1 -> 87 | C97: 800 Amp Service from MSB - 28 Containers | I97: ea | K97: =J97*H97 -> 0 | N97: =ROUND(L97*M97*H97,0) -> 0 | P97: =O97*N97 -> 0 | U97: 0 | V97: =H97*U97 -> 0 | W97: =V97+T97+P97+K97 -> 0
A98: =A97+1 -> 88 | V98: =H98*U98 -> 0 | W98: =V98+T98+P98+K98 -> 0
A99: =A98+1 -> 89 | V99: =H99*U99 -> 0 | W99: =V99+T99+P99+K99 -> 0
A100: =A99+1 -> 90 | V100: =H100*U100 -> 0 | W100: =V100+T100+P100+K100 -> 0 | X100: Mid South Number
A101: =A100+1 -> 91 | V101: =H101*U101 -> 0 | W101: =V101+T101+P101+K101 -> 0
A102: =A101+1 -> 92 | V102: =H102*U102 -> 0 | W102: =V102+T102+P102+K102 -> 0
...
