Workbook

Sheet Estimate
A3: The Alleato Group . 8383 Craig Street #150 . Indianapolis, IN . 46250
A5: Contact | B5: Brandon Clymer | C5: bclymer@alleatogroup.com | D5: 317.760.0088
A6: Contact | B6: AJ Taylor | C6: ataylor@alleatogroup.com | D6: 317.363.3396
A8: Project:
A9: Location:
A11: Division 01 General Conditions
A12: Total | B12: ='General Conditions'!C76 -> 0
A13: Division 02 Existing Conditions
B14: =QuantityTakeoff!Y25 -> 0 | C14: From Qty Sheet
B15: 0
A16: Total | B16: =SUBTOTAL(9,B14:B15) -> 0
A17: Division 03 Concrete
B18: =QuantityTakeoff!Y41 -> 0 | C18: From Qty Sheet
B19: 0
A20: Total | B20: =SUBTOTAL(9,B18:B19) -> 0
A21: Division 03.1 Precast
A22: Precast | C22: ATMI
A24: Total | B24: =SUBTOTAL(9,B22:B23) -> 0
A25: Division 04 Masonry
A26: Masonry | B26: =QuantityTakeoff!Y53 -> 0 | C26: From Qty Sheet
B27: 0
A28: Total | B28: =SUBTOTAL(9,B26:B27) -> 0
A29: Division 05 Metals
A30: bollards | B30: =QuantityTakeoff!Y60 -> 0 | C30: From Qty Sheet
B31: 0
B32: 0
A33: Total | B33: =SUBTOTAL(9,B30:B31) -> 0
A34: Division 06 Wood Plastics Composits
B35: =QuantityTakeoff!Y71 -> 0 | C35: From Qty Sheet
B36: 0
A37: Total | B37: =SUBTOTAL(9,B35:B36) -> 0
A38: Division 07 Thermal and Moisture Protection
B39: =QuantityTakeoff!Y87 -> 0 | C39: From Qty Sheet
B40: 0
B41: 0
B42: 0
A43: Total | B43: =SUBTOTAL(9,B39:B42) -> 0
A44: Division 08 Openings
B45: =QuantityTakeoff!Y98 -> 0 | C45: From Qty Sheet
B46: 0
B47: 0
B48: 0
A49: Total | B49: =SUBTOTAL(9,B45:B48) -> 0
A50: Division 09 Finishes
A51: Final Cleaning
B52: =QuantityTakeoff!Y113 -> 0 | C52: From Qty Sheet
A53: Tax | B53: =QuantityTakeoff!W314 -> 0 | C53: From Qty Sheet
B54: 0
B55: 0
B56: 0
A57: Total | B57: =ROUNDUP(SUBTOTAL(9,B51:B56), 0) -> 0
A58: Division 10 Specialties
B59: =QuantityTakeoff!Y137 -> 0
B60: 0
B61: 0
A62: Total | B62: =SUBTOTAL(9,B59:B61) -> 0
A63: Division 11 Equipment
B64: 0
B65: 0
B66: 0
B67: 0
A68: Total | B68: =SUBTOTAL(9,B64:B67) -> 0
A69: Division 12 Furnishings
B70: =QuantityTakeoff!Y156 -> 0
B71: 0
A72: Total | B72: =SUBTOTAL(9,B70:B71) -> 0
A73: Division 21 Fire Suppression
B74: =QuantityTakeoff!Y166 -> 0
B75: 0
A76: Total | B76: =SUBTOTAL(9,B74:B75) -> 0
A77: Division 22 Plumbing
B78: =QuantityTakeoff!Y171 -> 0
A80: Total | B80: =SUBTOTAL(9,B78:B79) -> 0
A81: Division 23 HVAC
B82: =QuantityTakeoff!Y190 -> 0
B83: 0
A84: Total | B84: =SUBTOTAL(9,B82) -> 0
A85: Division 26 Electrical
B86: =QuantityTakeoff!Y205 -> 0
B87: 0
A88: Total | B88: =SUBTOTAL(9,B86) -> 0
A89: Division 27 Communications
A92: Total | B92: =SUBTOTAL(9,B90) -> 0
A93: Division 28 Electronic Safety and Secutiry
B94: =QuantityTakeoff!Y237 -> 0
A96: Total | B96: =SUBTOTAL(9,B94:B95) -> 0
A97: Division 31 Earthwork
B98: =QuantityTakeoff!Y244 -> 0
B99: 0
B100: 0
B101: 0
B102: 0
A103: Total | B103: =SUBTOTAL(9,B98:B102) -> 0
A104: Division 31.10 Soil Stabilization
A107: Total | B107: =SUBTOTAL(9,B105:B106) -> 0
A108: Division 32 Exterior Improvements
B109: =QuantityTakeoff!Y260 -> 0
B110: 0
A111: Total | B111: =SUBTOTAL(9,B109:B110) -> 0
A112: Division 32.10 Paving
...

Sheet General Conditions
B1: Project Duration | D1: Months | F1: Weeks
A3: General Conditions | E3: Quantity | F3: Unit | G3: Rate
A4: 01-3120 | B4: Vice President | C4: =E4*G4 -> 0 | E4: =G1 -> 0 | F4: Weeks | G4: 3115
A5: 01-3126 | B5: Pre-construction | C5: =E5*G5 -> 0 | E5: =G1 -> 0 | F5: Weeks | G5: 2596
A6: 01-3127 | B6: Sr. Project Manager | C6: =E6*G6 -> 0 | E6: =G1 -> 0 | F6: Weeks | G6: 2800
A7: 01-3128 | B7: Project Manager | C7: =E7*G7 -> 0 | E7: =G1 -> 0 | F7: Weeks | G7: 2100
A8: 01-3129 | B8: Assistant Project Manager (APM) | C8: =E8*G8 -> 0 | E8: =G1 -> 0 | F8: Weeks | G8: 1500
A9: 01-3130 | B9: Project Engineer | C9: =E9*G9 -> 0 | E9: =G1 -> 0 | F9: Weeks | G9: 1100
A10: 01-3131 | B10: Field Engineer | C10: =E10*G10 -> 0 | E10: =G1 -> 0 | F10: Weeks | G10: 1100
A11: 01-3132 | B11: Intern | C11: =E11*G11 -> 0 | E11: =G1 -> 0 | F11: Weeks | G11: 850
A12: 01-3142 | B12: General Superintendent | C12: =E12*G12 -> 0 | E12: =G1 -> 0 | F12: Weeks | G12: 2800
A13: 01-3143 | B13: Sr. Superintendent | C13: =E13*G13 -> 0 | E13: =G1 -> 0 | F13: Weeks | G13: 2500
A14: 01-3144 | B14: Superintendent | C14: =E14*G14 -> 0 | E14: =G1 -> 0 | F14: Weeks | G14: 2100
A15: 01-3145 | B15: Assistant Superintendent | C15: =E15*G15 -> 0 | E15: =G1 -> 0 | F15: Weeks | G15: 650
A16: 01-3223 | B16: Construction Layout | C16: =E16*G16 -> 0 | E16: =E1 -> 0 | F16: Months | G16: 150
A17: 01-3236 | B17: Aerial & Periodic Drones | C17: =E17*G17 -> 0 | E17: =E1 -> 0 | F17: Months | G17: 350
A18: 01-3238 | B18: Jobsite Security | C18: =E18*G18 -> 0 | E18: 1 | F18: LS
A19: 01-3245 | B19: Office Supplies | C19: =E19*G19 -> 0 | E19: =E1 -> 0 | F19: Months | G19: 500
A20: 01-3247 | B20: Printing & Copying | C20: =E20*G20 -> 0 | E20: =E1 -> 0 | F20: Months | G20: 500
A21: 01-3249 | B21: Postage & Courier | C21: =E21*G21 -> 0 | E21: =E1 -> 0 | F21: Months | G21: 750
A22: 01-3329 | B22: LEED Documentation | C22: =E22*G22 -> 0 | E22: =E1 -> 0 | F22: Months | G22: 650
A23: 01-3514 | B23: Legal Fees | C23: =E23*G23 -> 0 | F23: LS | G23: 0
A24: 01-4123 | B24: Fees | C24: =E24*G24 -> 0 | F24: SF | G24: 1.25
A25: 01-4124 | B25: Sanitary Fees | C25: =E25*G25 -> 0 | F25: SF | G25: 1.25
A26: 01-4126 | B26: Permit Requirements | C26: =E26*G26 -> 0 | E26: 1 | F26: LS | G26: 0
A27: 01-4523 | B27: Testing and Inspections | C27: =E27*G27 -> 0 | E27: 1 | F27: LS | G27: 0
A28: 01-4533 | B28: Municipality Inspections | C28: =E28*G28 -> 0 | F28: EA | G28: 0
A29: 01-4613 | B29: Winter Conditions | C29: =E29*G29 -> 0 | E29: 1 | F29: LS | G29: 0
A30: 01-5113 | B30: Temporary Electric | C30: =E30*G30 -> 0 | E30: =E1 -> 0 | F30: Months | G30: 300
A31: 01-5116 | B31: Temporary Fire Protection | C31: =E31*G31 -> 0 | E31: =E1 -> 0 | F31: Months
A32: 01-5119 | B32: Temporary Fuel | C32: =E32*G32 -> 0 | E32: =E1 -> 0 | F32: Weeks | G32: 100
A33: 01-5123 | B33: Temporary HVAC | C33: =E33*G33 -> 0 | E33: =E1 -> 0 | F33: Months
A34: 01-5126 | B34: Temporary Lighting | C34: =E34*G34 -> 0 | E34: 1 | F34: LS
A35: 01-5129 | B35: Temporary Gas | C35: =E35*G35 -> 0 | E35: =E1 -> 0 | F35: Months | G35: 0
A36: 01-5133 | B36: Temporary Internet/Telecomm | C36: =E36*G36 -> 0 | E36: =E1 -> 0 | F36: Months | G36: 100
A37: 01-5136 | B37: Temporary Water | C37: =E37*G37 -> 0 | E37: =E1 -> 0 | F37: Months | G37: 0
A38: 01-5213 | B38: Field Offices | C38: =E38*G38 -> 0 | E38: =E1 -> 0 | F38: Months | G38: 0
A39: 01-5214 | B39: Temporary Storage | C39: =E39*G39 -> 0 | E39: =E1 -> 0 | F39: Months | G39: 0
A40: 01-5216 | B40: First Aid / Safety Supplies | C40: =E40*G40 -> 0 | E40: 0 | F40: LS | G40: 350
A41: 01-5217 | B41: Safety Inspections | C41: =E41*G41 -> 0 | E41: =E1 -> 0 | F41: Months | G41: 450
A42: 01-5219 | B42: Temporary Toilets | C42: =E42*G42 -> 0 | E42: =E1 -> 0 | F42: Months | G42: 0
A43: 01-5419 | B43: Temporary Cranes | C43: =E43*G43 -> 0 | E43: 1 | F43: LS
A44: 01-5423 | B44: Temp Scaffolding & Platforms | C44: =E44*G44 -> 0 | E44: 1 | F44: LS
A45: 01-5513 | B45: Temporary Access Roads | C45: =E45*G45 -> 0 | E45: 1 | F45: LS
A46: 01-5519 | B46: Temporary Parking Areas | C46: =E46*G46 -> 0 | E46: 1 | F46: LS
A47: 01-5623 | B47: Temporary Barricades | C47: =E47*G47 -> 0 | E47: 1 | F47: LS
A48: 01-5626 | B48: Tempoary Fencing | C48: =E48*G48 -> 0 | E48: 1 | F48: LF
A49: 01-5639 | B49: Temp Tree & Plant Protection | C49: =E49*G49 -> 0 | E49: 1 | F49: LS
A50: 01-5713 | B50: Temporary Erosion and Sediment | C50: =E50*G50 -> 0 | E50: 1 | F50: LS
A51: 01-5813 | B51: Temporary Project Signage | C51: =E51*G51 -> 0 | E51: 1 | F51: LS
A52: 01-6113 | B52: Software Licensing | C52: =E52*G52 -> 0 | E52: 1 | F52: LS
A53: 01-6115 | B53: Performance and Payment Bonds | C53: =E53*G53 -> 0 | E53: 1 | F53: LS
A54: 01-6119 | B54: Maintenenace Bond | C54: =E54*G54 -> 0 | E54: 1 | F54: LS
A55: 01-6500 | B55: Travel | C55: =E55*G55 -> 0 | E55: =E1 -> 0 | F55: Months
A56: 01-6502 | B56: Truck Allowance | C56: =E56*G56 -> 0 | E56: =E1 -> 0 | F56: Months
A57: 01-6503 | B57: Truck Fuel | C57: =E57*G57 -> 0 | E57: =E1 -> 0 | F57: Months
A58: 01-6504 | B58: Recruitment | C58: =E58*G58 -> 0 | E58: 1 | F58: LS
A59: 01-6505 | B59: Marketing | C59: =E59*G59 -> 0 | E59: 1 | F59: LS
A60: 01-7123 | B60: Construction Surveying | C60: =E60*G60 -> 0 | E60: 1 | F60: LS
A61: 01-7329 | B61: Cutting and Patching | C61: =E61*G61 -> 0 | E61: 1 | F61: LS
A62: 01-7333 | B62: Misc Small Tools | C62: =E62*G62 -> 0 | E62: =E1 -> 0 | F62: Months
A63: 01-7336 | B63: Equipment Rental | C63: =E63*G63 -> 0 | E63: =E1 -> 0 | F63: Months
A64: 01-7413 | B64: Progress Cleaning | C64: =E64*G64 -> 0 | E64: =E1 -> 0 | F64: Months
A65: 01-7416 | B65: Site Maintenance | C65: =E65*G65 -> 0 | E65: =E1 -> 0 | F65: Months
A66: 01-7419 | B66: Dumpsters | C66: =E66*G66 -> 0 | F66: EA
A67: 01-7423 | B67: Final Cleaning | C67: =E67*G67 -> 0 | F67: SF
A68: 01-7425 | B68: General Labor | C68: =E68*G68 -> 0 | E68: =E1 -> 0 | F68: Months
A69: 01-7433 | B69: Window Washing | C69: =E69*G69 -> 0 | F69: SF
A70: 01-7823 | B70: Operation and Maintenance Data | C70: =E70*G70 -> 0 | E70: 1 | F70: LS
A71: 01-7836 | B71: Warranties | C71: =E71*G71 -> 0 | E71: 1 | F71: LS
A72: 01-7841 | B72: Project Final Photos | C72: =E72*G72 -> 0 | E72: 1 | F72: LS
A73: 01-8113 | B73: Sust Design Reqmts/LEED Reqmts | C73: =E73*G73 -> 0 | E73: 1 | F73: LS
A74: 01-9119 | B74: Facility Commissioning | C74: =E74*G74 -> 0 | E74: 1 | F74: LS
A76: Total | C76: =ROUNDUP(SUM(C4:C74),0) -> 0

Sheet QuantityTakeoff
A2: Client: | F2: Job Name: | M2: Estimate Number:
A3: Location: | F3: Estimate Date:
A4: Estimator: | F4: Revision Date:
D6: Dimensions | J6: Material | M6: Labor | Q6: Equipment (incl fuel) | U6: Subcontract
A7: Line | B7: Division | C7: Description | D7: Length | E7: Width | F7: Depth | G7: No. of Ea. | H7: Quantity | I7: Unit | J7: Unit Price | K7: Cost | L7: Crew | M7: Hrs | N7: MH | O7: Rate | P7: Cost | Q7: Duration | R7: Unit | S7: Rate | T7: Cost | U7: Unit Price | V7: Cost | W7: Total Cost | X7: Comments
A8: 1 | B8: 00 Design | K8: =J8*H8 -> 0 | N8: =ROUND(L8*M8*H8,0) -> 0 | P8: =O8*N8 -> 0 | T8: =S8*Q8 -> 0 | V8: =H8*U8 -> 0 | W8: =V8+T8+P8+K8 -> 0 | Y8: =SUM(W8:W18) -> 0
A9: =A8+1 -> 2 | C9: Alleato Coordination | I9: lot | K9: =J9*H9 -> 0 | N9: =ROUND(L9*M9*H9,0) -> 0 | P9: =O9*N9 -> 0 | T9: =S9*Q9 -> 0 | V9: =H9*U9 -> 0 | W9: =V9+T9+P9+K9 -> 0
A10: =A9+1 -> 3 | C10: Boundary Survey | I10: lot | K10: =J10*H10 -> 0 | N10: =ROUND(L10*M10*H10,0) -> 0 | P10: =O10*N10 -> 0 | T10: =S10*Q10 -> 0 | V10: =H10*U10 -> 0 | W10: =V10+T10+P10+K10 -> 0
A11: =A10+1 -> 4 | C11: Topographic Survey | I11: lot | K11: =J11*H11 -> 0 | N11: =ROUND(L11*M11*H11,0) -> 0 | P11: =O11*N11 -> 0 | T11: =S11*Q11 -> 0 | V11: =H11*U11 -> 0 | W11: =V11+T11+P11+K11 -> 0
A12: =A11+1 -> 5 | C12: Geotechnical Survey | I12: lot | K12: =J12*H12 -> 0 | N12: =ROUND(L12*M12*H12,0) -> 0 | P12: =O12*N12 -> 0 | T12: =S12*Q12 -> 0 | V12: =H12*U12 -> 0 | W12: =V12+T12+P12+K12 -> 0
A13: =A12+1 -> 6 | C13: Civil Design | I13: lot | K13: =J13*H13 -> 0 | N13: =ROUND(L13*M13*H13,0) -> 0 | P13: =O13*N13 -> 0 | T13: =S13*Q13 -> 0 | V13: =H13*U13 -> 0 | W13: =V13+T13+P13+K13 -> 0
A14: =A13+1 -> 7 | C14: Architectural Design | I14: lot | K14: =J14*H14 -> 0 | N14: =ROUND(L14*M14*H14,0) -> 0 | P14: =O14*N14 -> 0 | T14: =S14*Q14 -> 0 | V14: =H14*U14 -> 0 | W14: =V14+T14+P14+K14 -> 0
A15: =A14+1 -> 8 | C15: Structural | I15: lot | K15: =J15*H15 -> 0 | N15: =ROUND(L15*M15*H15,0) -> 0 | P15: =O15*N15 -> 0 | T15: =S15*Q15 -> 0 | V15: =H15*U15 -> 0 | W15: =V15+T15+P15+K15 -> 0
A16: =A15+1 -> 9 | C16: MEP Design | I16: lot | K16: =J16*H16 -> 0 | N16: =ROUND(L16*M16*H16,0) -> 0 | P16: =O16*N16 -> 0 | T16: =S16*Q16 -> 0 | V16: =H16*U16 -> 0 | W16: =V16+T16+P16+K16 -> 0
A17: =A16+1 -> 10 | C17: Landscape Design | I17: lot | K17: =J17*H17 -> 0 | N17: =ROUND(L17*M17*H17,0) -> 0 | P17: =O17*N17 -> 0 | T17: =S17*Q17 -> 0 | V17: =H17*U17 -> 0 | W17: =V17+T17+P17+K17 -> 0
A18: =A17+1 -> 11 | I18: lot | K18: =J18*H18 -> 0 | N18: =ROUND(L18*M18*H18,0) -> 0 | P18: =O18*N18 -> 0 | T18: =S18*Q18 -> 0 | V18: =H18*U18 -> 0 | W18: =V18+T18+P18+K18 -> 0
A19: =A18+1 -> 12 | B19: 01 General Conditions | K19: =J19*H19 -> 0 | N19: =ROUND(L19*M19*H19,0) -> 0 | P19: =O19*N19 -> 0 | T19: =S19*Q19 -> 0 | V19: =H19*U19 -> 0 | W19: =V19+T19+P19+K19 -> 0
A20: =A19+1 -> 13 | B20: 01-3120 | C20: =IFERROR(VLOOKUP(B20,'Importer Data Fields'!C2:D358,2,0),"") -> Vice President | I20: lot | K20: =J20*H20 -> 0 | N20: =ROUND(L20*M20*H20,0) -> 0 | P20: =O20*N20 -> 0 | T20: =S20*Q20 -> 0 | V20: =H20*U20 -> 0 | W20: =V20+T20+P20+K20 -> 0
A21: =A20+1 -> 14 | C21: =IFERROR(VLOOKUP(B21,'Importer Data Fields'!C3:D359,2,0),"") | I21: lot | K21: =J21*H21 -> 0 | N21: =ROUND(L21*M21*H21,0) -> 0 | P21: =O21*N21 -> 0 | T21: =S21*Q21 -> 0 | V21: =H21*U21 -> 0 | W21: =V21+T21+P21+K21 -> 0
A22: =A21+1 -> 15 | B22: 01-4126 | C22: =IFERROR(VLOOKUP(B22,'Importer Data Fields'!C4:D360,2,0),"") -> Permit Requirements | I22: lot | K22: =J22*H22 -> 0 | N22: =ROUND(L22*M22*H22,0) -> 0 | P22: =O22*N22 -> 0 | T22: =S22*Q22 -> 0 | V22: =H22*U22 -> 0 | W22: =V22+T22+P22+K22 -> 0
A23: =A22+1 -> 16 | B23: 01-4126 | C23: =IFERROR(VLOOKUP(B23,'Importer Data Fields'!C5:D361,2,0),"") -> Permit Requirements | I23: lot | K23: =J23*H23 -> 0 | N23: =ROUND(L23*M23*H23,0) -> 0 | P23: =O23*N23 -> 0 | T23: =S23*Q23 -> 0 | V23: =H23*U23 -> 0 | W23: =V23+T23+P23+K23 -> 0
A24: =A23+1 -> 17 | C24: =IFERROR(VLOOKUP(B24,'Importer Data Fields'!C6:D362,2,0),"") | K24: =J24*H24 -> 0 | N24: =ROUND(L24*M24*H24,0) -> 0 | P24: =O24*N24 -> 0 | T24: =S24*Q24 -> 0 | V24: =H24*U24 -> 0 | W24: =V24+T24+P24+K24 -> 0
A25: =A24+1 -> 18 | B25: 02 Existing Conditions | K25: =J25*H25 -> 0 | N25: =ROUND(L25*M25*H25,0) -> 0 | P25: =O25*N25 -> 0 | T25: =S25*Q25 -> 0 | V25: =H25*U25 -> 0 | W25: =V25+T25+P25+K25 -> 0 | Y25: =SUM(W25:W40) -> 0
A26: =A25+1 -> 19 | B26: 02-0150 | C26: =IFERROR(VLOOKUP(B26,'Importer Data Fields'!C:D,2,0),"") -> Maintenance & Site Remediation | I26: lot | K26: =J26*H26 -> 0 | N26: =ROUND(L26*M26*H26,0) -> 0 | P26: =O26*N26 -> 0 | T26: =S26*Q26 -> 0 | V26: =H26*U26 -> 0 | W26: =V26+T26+P26+K26 -> 0
A27: =A26+1 -> 20 | B27: 02-4116 | C27: =IFERROR(VLOOKUP(B27,'Importer Data Fields'!C:D,2,0),"") -> Structure Demolition | I27: lot | K27: =J27*H27 -> 0 | N27: =ROUND(L27*M27*H27,0) -> 0 | P27: =O27*N27 -> 0 | T27: =S27*Q27 -> 0 | V27: =H27*U27 -> 0 | W27: =V27+T27+P27+K27 -> 0
A28: =A27+1 -> 21 | B28: 02-4116 | C28: =IFERROR(VLOOKUP(B28,'Importer Data Fields'!C:D,2,0),"") -> Structure Demolition | I28: lot | K28: =J28*H28 -> 0 | N28: =ROUND(L28*M28*H28,0) -> 0 | P28: =O28*N28 -> 0 | T28: =S28*Q28 -> 0 | V28: =H28*U28 -> 0 | W28: =V28+T28+P28+K28 -> 0
A29: =A28+1 -> 22 | B29: 02-4113 | C29: =IFERROR(VLOOKUP(B29,'Importer Data Fields'!C:D,2,0),"") -> Selective Interior Demolition | I29: lf | K29: =J29*H29 -> 0 | N29: =ROUND(L29*M29*H29,0) -> 0 | P29: =O29*N29 -> 0 | T29: =S29*Q29 -> 0 | V29: =H29*U29 -> 0 | W29: =V29+T29+P29+K29 -> 0
A30: =A29+1 -> 23 | B30: 02-4113 | C30: =IFERROR(VLOOKUP(B30,'Importer Data Fields'!C:D,2,0),"") -> Selective Interior Demolition | I30: lot | K30: =J30*H30 -> 0 | N30: =ROUND(L30*M30*H30,0) -> 0 | P30: =O30*N30 -> 0 | T30: =S30*Q30 -> 0 | V30: =H30*U30 -> 0 | W30: =V30+T30+P30+K30 -> 0
A31: =A30+1 -> 24 | B31: 02-4113 | C31: =IFERROR(VLOOKUP(B31,'Importer Data Fields'!C:D,2,0),"") -> Selective Interior Demolition | I31: sf | K31: =J31*H31 -> 0 | N31: =ROUND(L31*M31*H31,0) -> 0 | P31: =O31*N31 -> 0 | T31: =S31*Q31 -> 0 | V31: =H31*U31 -> 0 | W31: =V31+T31+P31+K31 -> 0
A32: =A31+1 -> 25 | B32: 02-4116 | C32: =IFERROR(VLOOKUP(B32,'Importer Data Fields'!C:D,2,0),"") -> Structure Demolition | I32: lot | K32: =J32*H32 -> 0 | N32: =ROUND(L32*M32*H32,0) -> 0 | P32: =O32*N32 -> 0 | T32: =S32*Q32 -> 0 | V32: =H32*U32 -> 0 | W32: =V32+T32+P32+K32 -> 0
A33: =A32+1 -> 26 | B33: 02-4113 | C33: =IFERROR(VLOOKUP(B33,'Importer Data Fields'!C:D,2,0),"") -> Selective Interior Demolition | I33: lot | K33: =J33*H33 -> 0 | N33: =ROUND(L33*M33*H33,0) -> 0 | P33: =O33*N33 -> 0 | T33: =S33*Q33 -> 0 | V33: =H33*U33 -> 0 | W33: =V33+T33+P33+K33 -> 0
A34: =A33+1 -> 27 | B34: 02-2219 | C34: =IFERROR(VLOOKUP(B34,'Importer Data Fields'!C:D,2,0),"") -> Traffic Assessment | K34: =J34*H34 -> 0 | N34: =ROUND(L34*M34*H34,0) -> 0 | P34: =O34*N34 -> 0 | T34: =S34*Q34 -> 0 | V34: =H34*U34 -> 0 | W34: =V34+T34+P34+K34 -> 0
A35: =A34+1 -> 28 | B35: 02-2400 | C35: =IFERROR(VLOOKUP(B35,'Importer Data Fields'!C:D,2,0),"") -> Environmental Assessments | I35: lf | K35: =J35*H35 -> 0 | N35: =ROUND(L35*M35*H35,0) -> 0 | P35: =O35*N35 -> 0 | T35: =S35*Q35 -> 0 | V35: =H35*U35 -> 0 | W35: =V35+T35+P35+K35 -> 0
A36: =A35+1 -> 29 | B36: 02-4116 | C36: =IFERROR(VLOOKUP(B36,'Importer Data Fields'!C:D,2,0),"") -> Structure Demolition | I36: lot | K36: =J36*H36 -> 0 | N36: =ROUND(L36*M36*H36,0) -> 0 | P36: =O36*N36 -> 0 | T36: =S36*Q36 -> 0 | V36: =H36*U36 -> 0 | W36: =V36+T36+P36+K36 -> 0
A37: =A36+1 -> 30 | C37: =IFERROR(VLOOKUP(B37,'Importer Data Fields'!C:D,2,0),"") | I37: lot | K37: =J37*H37 -> 0 | N37: =ROUND(L37*M37*H37,0) -> 0 | P37: =O37*N37 -> 0 | T37: =S37*Q37 -> 0 | V37: =H37*U37 -> 0 | W37: =V37+T37+P37+K37 -> 0
A38: =A37+1 -> 31 | B38: 02-0150 | C38: =IFERROR(VLOOKUP(B38,'Importer Data Fields'!C:D,2,0),"") -> Maintenance & Site Remediation | I38: lot | K38: =J38*H38 -> 0 | N38: =ROUND(L38*M38*H38,0) -> 0 | P38: =O38*N38 -> 0 | T38: =S38*Q38 -> 0 | V38: =H38*U38 -> 0 | W38: =V38+T38+P38+K38 -> 0
A39: =A38+1 -> 32 | C39: =IFERROR(VLOOKUP(B39,'Importer Data Fields'!C:D,2,0),"") | I39: sf | K39: =J39*H39 -> 0 | N39: =ROUND(L39*M39*H39,0) -> 0 | P39: =O39*N39 -> 0 | T39: =S39*Q39 -> 0 | V39: =H39*U39 -> 0 | W39: =V39+T39+P39+K39 -> 0
A40: =A39+1 -> 33 | C40: =IFERROR(VLOOKUP(B40,'Importer Data Fields'!C:D,2,0),"") | I40: lot | K40: =J40*H40 -> 0 | N40: =ROUND(L40*M40*H40,0) -> 0 | P40: =O40*N40 -> 0 | T40: =S40*Q40 -> 0 | V40: =H40*U40 -> 0 | W40: =V40+T40+P40+K40 -> 0
A41: =A40+1 -> 34 | B41: 03 Concrete | K41: =J41*H41 -> 0 | N41: =ROUND(L41*M41*H41,0) -> 0 | P41: =O41*N41 -> 0 | T41: =S41*Q41 -> 0 | V41: =H41*U41 -> 0 | W41: =V41+T41+P41+K41 -> 0 | Y41: =SUM(W41:W52) -> 0
A42: =A41+1 -> 35 | C42: =IFERROR(VLOOKUP(B42,'Importer Data Fields'!C:D,2,0),"") | K42: =J42*H42 -> 0 | N42: =ROUND(L42*M42*H42,0) -> 0 | P42: =O42*N42 -> 0 | T42: =S42*Q42 -> 0 | V42: =H42*U42 -> 0 | W42: =V42+T42+P42+K42 -> 0
A43: =A42+1 -> 36 | C43: =IFERROR(VLOOKUP(B43,'Importer Data Fields'!C:D,2,0),"") | I43: sf | K43: =J43*H43 -> 0 | N43: =ROUND(L43*M43*H43,0) -> 0 | P43: =O43*N43 -> 0 | T43: =S43*Q43 -> 0 | V43: =H43*U43 -> 0 | W43: =V43+T43+P43+K43 -> 0
A44: =A43+1 -> 37 | C44: =IFERROR(VLOOKUP(B44,'Importer Data Fields'!C:D,2,0),"") | I44: sf | K44: =J44*H44 -> 0 | N44: =ROUND(L44*M44*H44,0) -> 0 | P44: =O44*N44 -> 0 | T44: =S44*Q44 -> 0 | V44: =H44*U44 -> 0 | W44: =V44+T44+P44+K44 -> 0
A45: =A44+1 -> 38 | C45: =IFERROR(VLOOKUP(B45,'Importer Data Fields'!C:D,2,0),"") | I45: lf | K45: =J45*H45 -> 0 | N45: =ROUND(L45*M45*H45,0) -> 0 | P45: =O45*N45 -> 0 | T45: =S45*Q45 -> 0 | V45: =H45*U45 -> 0 | W45: =V45+T45+P45+K45 -> 0
A46: =A45+1 -> 39 | C46: =IFERROR(VLOOKUP(B46,'Importer Data Fields'!C:D,2,0),"") | I46: ea | K46: =J46*H46 -> 0 | N46: =ROUND(L46*M46*H46,0) -> 0 | P46: =O46*N46 -> 0 | T46: =S46*Q46 -> 0 | V46: =H46*U46 -> 0 | W46: =V46+T46+P46+K46 -> 0
A47: =A46+1 -> 40 | C47: =IFERROR(VLOOKUP(B47,'Importer Data Fields'!C:D,2,0),"") | I47: cy | K47: =J47*H47 -> 0 | N47: =ROUND(L47*M47*H47,0) -> 0 | P47: =O47*N47 -> 0 | T47: =S47*Q47 -> 0 | V47: =H47*U47 -> 0 | W47: =V47+T47+P47+K47 -> 0
A48: =A47+1 -> 41 | C48: =IFERROR(VLOOKUP(B48,'Importer Data Fields'!C:D,2,0),"") | I48: sf | K48: =J48*H48 -> 0 | N48: =ROUND(L48*M48*H48,0) -> 0 | P48: =O48*N48 -> 0 | T48: =S48*Q48 -> 0 | V48: =H48*U48 -> 0 | W48: =V48+T48+P48+K48 -> 0
A49: =A48+1 -> 42 | C49: =IFERROR(VLOOKUP(B49,'Importer Data Fields'!C:D,2,0),"") | I49: sf | K49: =J49*H49 -> 0 | N49: =ROUND(L49*M49*H49,0) -> 0 | P49: =O49*N49 -> 0 | T49: =S49*Q49 -> 0 | V49: =H49*U49 -> 0 | W49: =V49+T49+P49+K49 -> 0
A50: =A49+1 -> 43 | B50: 03-2000 | C50: =IFERROR(VLOOKUP(B50,'Importer Data Fields'!C:D,2,0),"") -> Foundations | I50: ea | K50: =J50*H50 -> 0 | N50: =ROUND(L50*M50*H50,0) -> 0 | P50: =O50*N50 -> 0 | T50: =S50*Q50 -> 0 | V50: =H50*U50 -> 0 | W50: =V50+T50+P50+K50 -> 0
A51: =A50+1 -> 44 | B51: 03-2500 | C51: =IFERROR(VLOOKUP(B51,'Importer Data Fields'!C:D,2,0),"") -> Concrete Subbase | I51: lot | K51: =J51*H51 -> 0 | N51: =ROUND(L51*M51*H51,0) -> 0 | P51: =O51*N51 -> 0 | T51: =S51*Q51 -> 0 | V51: =H51*U51 -> 0 | W51: =V51+T51+P51+K51 -> 0
A52: =A51+1 -> 45 | C52: =IFERROR(VLOOKUP(B52,'Importer Data Fields'!C:D,2,0),"") | I52: lot | K52: =J52*H52 -> 0 | N52: =ROUND(L52*M52*H52,0) -> 0 | P52: =O52*N52 -> 0 | T52: =S52*Q52 -> 0 | V52: =H52*U52 -> 0 | W52: =V52+T52+P52+K52 -> 0
A53: =A52+1 -> 46 | B53: 04 Masonry | K53: =J53*H53 -> 0 | N53: =ROUND(L53*M53*H53,0) -> 0 | P53: =O53*N53 -> 0 | T53: =S53*Q53 -> 0 | V53: =H53*U53 -> 0 | W53: =V53+T53+P53+K53 -> 0 | Y53: =SUM(W53:W59) -> 0
A54: =A53+1 -> 47 | C54: =IFERROR(VLOOKUP(B54,'Importer Data Fields'!C:D,2,0),"") | K54: =J54*H54 -> 0 | N54: =ROUND(L54*M54*H54,0) -> 0 | P54: =O54*N54 -> 0 | T54: =S54*Q54 -> 0 | V54: =H54*U54 -> 0 | W54: =V54+T54+P54+K54 -> 0
A55: =A54+1 -> 48 | B55: 04-2000 | C55: =IFERROR(VLOOKUP(B55,'Importer Data Fields'!C:D,2,0),"") -> Unit Masonry-Brick | I55: sf | K55: =J55*H55 -> 0 | N55: =ROUND(L55*M55*H55,0) -> 0 | P55: =O55*N55 -> 0 | T55: =S55*Q55 -> 0 | V55: =H55*U55 -> 0 | W55: =V55+T55+P55+K55 -> 0
A56: =A55+1 -> 49 | C56: =IFERROR(VLOOKUP(B56,'Importer Data Fields'!C:D,2,0),"") | I56: sf | K56: =J56*H56 -> 0 | N56: =ROUND(L56*M56*H56,0) -> 0 | P56: =O56*N56 -> 0 | T56: =S56*Q56 -> 0 | V56: =H56*U56 -> 0 | W56: =V56+T56+P56+K56 -> 0
A57: =A56+1 -> 50 | C57: =IFERROR(VLOOKUP(B57,'Importer Data Fields'!C:D,2,0),"") | K57: =J57*H57 -> 0 | N57: =ROUND(L57*M57*H57,0) -> 0 | P57: =O57*N57 -> 0 | T57: =S57*Q57 -> 0 | V57: =H57*U57 -> 0 | W57: =V57+T57+P57+K57 -> 0
A58: =A57+1 -> 51 | C58: =IFERROR(VLOOKUP(B58,'Importer Data Fields'!C:D,2,0),"") | K58: =J58*H58 -> 0 | N58: =ROUND(L58*M58*H58,0) -> 0 | P58: =O58*N58 -> 0 | T58: =S58*Q58 -> 0 | V58: =H58*U58 -> 0 | W58: =V58+T58+P58+K58 -> 0
A59: =A58+1 -> 52 | C59: =IFERROR(VLOOKUP(B59,'Importer Data Fields'!C:D,2,0),"") | K59: =J59*H59 -> 0 | N59: =ROUND(L59*M59*H59,0) -> 0 | P59: =O59*N59 -> 0 | T59: =S59*Q59 -> 0 | V59: =H59*U59 -> 0 | W59: =V59+T59+P59+K59 -> 0
A60: =A59+1 -> 53 | B60: 05 Metals | K60: =J60*H60 -> 0 | N60: =ROUND(L60*M60*H60,0) -> 0 | P60: =O60*N60 -> 0 | T60: =S60*Q60 -> 0 | V60: =H60*U60 -> 0 | W60: =V60+T60+P60+K60 -> 0 | Y60: =SUM(W60:W70) -> 0
A61: =A60+1 -> 54 | C61: =IFERROR(VLOOKUP(B61,'Importer Data Fields'!C:D,2,0),"") | I61: ea | K61: =J61*H61 -> 0 | N61: =ROUND(L61*M61*H61,0) -> 0 | P61: =O61*N61 -> 0 | T61: =S61*Q61 -> 0 | V61: =H61*U61 -> 0 | W61: =V61+T61+P61+K61 -> 0
A62: =A61+1 -> 55 | C62: =IFERROR(VLOOKUP(B62,'Importer Data Fields'!C:D,2,0),"") | K62: =J62*H62 -> 0 | N62: =ROUND(L62*M62*H62,0) -> 0 | P62: =O62*N62 -> 0 | T62: =S62*Q62 -> 0 | V62: =H62*U62 -> 0 | W62: =V62+T62+P62+K62 -> 0
A63: =A62+1 -> 56 | B63: 05-1200 | C63: =IFERROR(VLOOKUP(B63,'Importer Data Fields'!C:D,2,0),"") -> Structural Steel Framing | I63: lot | K63: =J63*H63 -> 0 | N63: =ROUND(L63*M63*H63,0) -> 0 | P63: =O63*N63 -> 0 | T63: =S63*Q63 -> 0 | V63: =H63*U63 -> 0 | W63: =V63+T63+P63+K63 -> 0
A64: =A63+1 -> 57 | C64: =IFERROR(VLOOKUP(B64,'Importer Data Fields'!C:D,2,0),"") | K64: =J64*H64 -> 0 | N64: =ROUND(L64*M64*H64,0) -> 0 | P64: =O64*N64 -> 0 | T64: =S64*Q64 -> 0 | V64: =H64*U64 -> 0 | W64: =V64+T64+P64+K64 -> 0
A65: =A64+1 -> 58 | C65: =IFERROR(VLOOKUP(B65,'Importer Data Fields'!C:D,2,0),"") | K65: =J65*H65 -> 0 | N65: =ROUND(L65*M65*H65,0) -> 0 | P65: =O65*N65 -> 0 | T65: =S65*Q65 -> 0 | V65: =H65*U65 -> 0 | W65: =V65+T65+P65+K65 -> 0
A66: =A65+1 -> 59 | C66: =IFERROR(VLOOKUP(B66,'Importer Data Fields'!C:D,2,0),"") | K66: =J66*H66 -> 0 | N66: =ROUND(L66*M66*H66,0) -> 0 | P66: =O66*N66 -> 0 | T66: =S66*Q66 -> 0 | V66: =H66*U66 -> 0 | W66: =V66+T66+P66+K66 -> 0
A67: =A66+1 -> 60 | C67: =IFERROR(VLOOKUP(B67,'Importer Data Fields'!C:D,2,0),"") | K67: =J67*H67 -> 0 | N67: =ROUND(L67*M67*H67,0) -> 0 | P67: =O67*N67 -> 0 | T67: =S67*Q67 -> 0 | V67: =H67*U67 -> 0 | W67: =V67+T67+P67+K67 -> 0
A68: =A67+1 -> 61 | C68: =IFERROR(VLOOKUP(B68,'Importer Data Fields'!C:D,2,0),"") | K68: =J68*H68 -> 0 | N68: =ROUND(L68*M68*H68,0) -> 0 | P68: =O68*N68 -> 0 | T68: =S68*Q68 -> 0 | V68: =H68*U68 -> 0 | W68: =V68+T68+P68+K68 -> 0
A69: =A68+1 -> 62 | C69: =IFERROR(VLOOKUP(B69,'Importer Data Fields'!C:D,2,0),"") | K69: =J69*H69 -> 0 | N69: =ROUND(L69*M69*H69,0) -> 0 | P69: =O69*N69 -> 0 | T69: =S69*Q69 -> 0 | V69: =H69*U69 -> 0 | W69: =V69+T69+P69+K69 -> 0
A70: =A69+1 -> 63 | C70: =IFERROR(VLOOKUP(B70,'Importer Data Fields'!C:D,2,0),"") | K70: =J70*H70 -> 0 | N70: =ROUND(L70*M70*H70,0) -> 0 | P70: =O70*N70 -> 0 | T70: =S70*Q70 -> 0 | V70: =H70*U70 -> 0 | W70: =V70+T70+P70+K70 -> 0
A71: =A70+1 -> 64 | B71: 06 Wood Plastics Composits | K71: =J71*H71 -> 0 | N71: =ROUND(L71*M71*H71,0) -> 0 | P71: =O71*N71 -> 0 | T71: =S71*Q71 -> 0 | V71: =H71*U71 -> 0 | W71: =V71+T71+P71+K71 -> 0 | Y71: =SUM(W71:W86) -> 0
A72: =A71+1 -> 65 | B72: 06-1100 | C72: =IFERROR(VLOOKUP(B72,'Importer Data Fields'!C:D,2,0),"") -> Wood Framing | I72: lot | K72: =J72*H72 -> 0 | N72: =ROUND(L72*M72*H72,0) -> 0 | P72: =O72*N72 -> 0 | T72: =S72*Q72 -> 0 | V72: =H72*U72 -> 0 | W72: =V72+T72+P72+K72 -> 0
A73: =A72+1 -> 66 | B73: 06-1100 | C73: =IFERROR(VLOOKUP(B73,'Importer Data Fields'!C:D,2,0),"") -> Wood Framing | I73: lot | K73: =J73*H73 -> 0 | N73: =ROUND(L73*M73*H73,0) -> 0 | P73: =O73*N73 -> 0 | T73: =S73*Q73 -> 0 | V73: =H73*U73 -> 0 | W73: =V73+T73+P73+K73 -> 0
A74: =A73+1 -> 67 | C74: =IFERROR(VLOOKUP(B74,'Importer Data Fields'!C:D,2,0),"") | I74: lot | K74: =J74*H74 -> 0 | N74: =ROUND(L74*M74*H74,0) -> 0 | P74: =O74*N74 -> 0 | T74: =S74*Q74 -> 0 | V74: =H74*U74 -> 0 | W74: =V74+T74+P74+K74 -> 0
A75: =A74+1 -> 68 | B75: 06-1100 | C75: =IFERROR(VLOOKUP(B75,'Importer Data Fields'!C:D,2,0),"") -> Wood Framing | I75: lot | K75: =J75*H75 -> 0 | N75: =ROUND(L75*M75*H75,0) -> 0 | P75: =O75*N75 -> 0 | T75: =S75*Q75 -> 0 | V75: =H75*U75 -> 0 | W75: =V75+T75+P75+K75 -> 0
A76: =A75+1 -> 69 | C76: =IFERROR(VLOOKUP(B76,'Importer Data Fields'!C:D,2,0),"") | I76: lot | K76: =J76*H76 -> 0 | N76: =ROUND(L76*M76*H76,0) -> 0 | P76: =O76*N76 -> 0 | T76: =S76*Q76 -> 0 | V76: =H76*U76 -> 0 | W76: =V76+T76+P76+K76 -> 0
A77: =A76+1 -> 70 | C77: =IFERROR(VLOOKUP(B77,'Importer Data Fields'!C:D,2,0),"") | I77: lot | K77: =J77*H77 -> 0 | N77: =ROUND(L77*M77*H77,0) -> 0 | P77: =O77*N77 -> 0 | T77: =S77*Q77 -> 0 | V77: =H77*U77 -> 0 | W77: =V77+T77+P77+K77 -> 0
A78: =A77+1 -> 71 | C78: =IFERROR(VLOOKUP(B78,'Importer Data Fields'!C:D,2,0),"") | I78: lot | K78: =J78*H78 -> 0 | N78: =ROUND(L78*M78*H78,0) -> 0 | P78: =O78*N78 -> 0 | T78: =S78*Q78 -> 0 | V78: =H78*U78 -> 0 | W78: =V78+T78+P78+K78 -> 0
A79: =A78+1 -> 72 | C79: =IFERROR(VLOOKUP(B79,'Importer Data Fields'!C:D,2,0),"") | I79: lot | K79: =J79*H79 -> 0 | N79: =ROUND(L79*M79*H79,0) -> 0 | P79: =O79*N79 -> 0 | T79: =S79*Q79 -> 0 | V79: =H79*U79 -> 0 | W79: =V79+T79+P79+K79 -> 0
A80: =A79+1 -> 73 | C80: =IFERROR(VLOOKUP(B80,'Importer Data Fields'!C:D,2,0),"") | I80: lot | K80: =J80*H80 -> 0 | N80: =ROUND(L80*M80*H80,0) -> 0 | P80: =O80*N80 -> 0 | T80: =S80*Q80 -> 0 | V80: =H80*U80 -> 0 | W80: =V80+T80+P80+K80 -> 0
A81: =A80+1 -> 74 | C81: =IFERROR(VLOOKUP(B81,'Importer Data Fields'!C:D,2,0),"") | K81: =J81*H81 -> 0 | N81: =ROUND(L81*M81*H81,0) -> 0 | P81: =O81*N81 -> 0 | T81: =S81*Q81 -> 0 | V81: =H81*U81 -> 0 | W81: =V81+T81+P81+K81 -> 0
A82: =A81+1 -> 75 | C82: =IFERROR(VLOOKUP(B82,'Importer Data Fields'!C:D,2,0),"") | I82: ea | K82: =J82*H82 -> 0 | N82: =ROUND(L82*M82*H82,0) -> 0 | P82: =O82*N82 -> 0 | T82: =S82*Q82 -> 0 | V82: =H82*U82 -> 0 | W82: =V82+T82+P82+K82 -> 0
A83: =A82+1 -> 76 | C83: =IFERROR(VLOOKUP(B83,'Importer Data Fields'!C:D,2,0),"") | I83: ea | K83: =J83*H83 -> 0 | N83: =ROUND(L83*M83*H83,0) -> 0 | P83: =O83*N83 -> 0 | T83: =S83*Q83 -> 0 | V83: =H83*U83 -> 0 | W83: =V83+T83+P83+K83 -> 0
A84: =A83+1 -> 77 | C84: =IFERROR(VLOOKUP(B84,'Importer Data Fields'!C:D,2,0),"") | I84: ea | K84: =J84*H84 -> 0 | N84: =ROUND(L84*M84*H84,0) -> 0 | P84: =O84*N84 -> 0 | T84: =S84*Q84 -> 0 | V84: =H84*U84 -> 0 | W84: =V84+T84+P84+K84 -> 0
A85: =A84+1 -> 78 | C85: =IFERROR(VLOOKUP(B85,'Importer Data Fields'!C:D,2,0),"") | I85: ea | K85: =J85*H85 -> 0 | N85: =ROUND(L85*M85*H85,0) -> 0 | P85: =O85*N85 -> 0 | T85: =S85*Q85 -> 0 | V85: =H85*U85 -> 0 | W85: =V85+T85+P85+K85 -> 0
A86: =A85+1 -> 79 | C86: =IFERROR(VLOOKUP(B86,'Importer Data Fields'!C:D,2,0),"") | K86: =J86*H86 -> 0 | N86: =ROUND(L86*M86*H86,0) -> 0 | P86: =O86*N86 -> 0 | T86: =S86*Q86 -> 0 | V86: =H86*U86 -> 0 | W86: =V86+T86+P86+K86 -> 0
A87: =A86+1 -> 80 | B87: 07 Thermal and Moisture Protection | K87: =J87*H87 -> 0 | N87: =ROUND(L87*M87*H87,0) -> 0 | P87: =O87*N87 -> 0 | T87: =S87*Q87 -> 0 | V87: =H87*U87 -> 0 | W87: =V87+T87+P87+K87 -> 0 | Y87: =SUM(W87:W97) -> 0
A88: =A87+1 -> 81 | C88: =IFERROR(VLOOKUP(B88,'Importer Data Fields'!C:D,2,0),"") | I88: sf | K88: =J88*H88 -> 0 | N88: =ROUND(L88*M88*H88,0) -> 0 | P88: =O88*N88 -> 0 | T88: =S88*Q88 -> 0 | V88: =H88*U88 -> 0 | W88: =V88+T88+P88+K88 -> 0
A89: =A88+1 -> 82 | C89: =IFERROR(VLOOKUP(B89,'Importer Data Fields'!C:D,2,0),"") | I89: lf | K89: =J89*H89 -> 0 | N89: =ROUND(L89*M89*H89,0) -> 0 | P89: =O89*N89 -> 0 | T89: =S89*Q89 -> 0 | V89: =H89*U89 -> 0 | W89: =V89+T89+P89+K89 -> 0
A90: =A89+1 -> 83 | C90: =IFERROR(VLOOKUP(B90,'Importer Data Fields'!C:D,2,0),"") | I90: ea | K90: =J90*H90 -> 0 | N90: =ROUND(L90*M90*H90,0) -> 0 | P90: =O90*N90 -> 0 | T90: =S90*Q90 -> 0 | V90: =H90*U90 -> 0 | W90: =V90+T90+P90+K90 -> 0
A91: =A90+1 -> 84 | C91: =IFERROR(VLOOKUP(B91,'Importer Data Fields'!C:D,2,0),"") | I91: lot | K91: =J91*H91 -> 0 | N91: =ROUND(L91*M91*H91,0) -> 0 | P91: =O91*N91 -> 0 | T91: =S91*Q91 -> 0 | V91: =H91*U91 -> 0 | W91: =V91+T91+P91+K91 -> 0
A92: =A91+1 -> 85 | C92: =IFERROR(VLOOKUP(B92,'Importer Data Fields'!C:D,2,0),"") | I92: lot | K92: =J92*H92 -> 0 | N92: =ROUND(L92*M92*H92,0) -> 0 | P92: =O92*N92 -> 0 | T92: =S92*Q92 -> 0 | V92: =H92*U92 -> 0 | W92: =V92+T92+P92+K92 -> 0
A93: =A92+1 -> 86 | C93: =IFERROR(VLOOKUP(B93,'Importer Data Fields'!C:D,2,0),"") | I93: ea | K93: =J93*H93 -> 0 | N93: =ROUND(L93*M93*H93,0) -> 0 | P93: =O93*N93 -> 0 | T93: =S93*Q93 -> 0 | V93: =H93*U93 -> 0 | W93: =V93+T93+P93+K93 -> 0
A94: =A93+1 -> 87 | C94: =IFERROR(VLOOKUP(B94,'Importer Data Fields'!C:D,2,0),"") | I94: ea | K94: =J94*H94 -> 0 | N94: =ROUND(L94*M94*H94,0) -> 0 | P94: =O94*N94 -> 0 | T94: =S94*Q94 -> 0 | V94: =H94*U94 -> 0 | W94: =V94+T94+P94+K94 -> 0
A95: =A94+1 -> 88 | C95: =IFERROR(VLOOKUP(B95,'Importer Data Fields'!C:D,2,0),"") | I95: lot | K95: =J95*H95 -> 0 | N95: =ROUND(L95*M95*H95,0) -> 0 | P95: =O95*N95 -> 0 | T95: =S95*Q95 -> 0 | V95: =H95*U95 -> 0 | W95: =V95+T95+P95+K95 -> 0
A96: =A95+1 -> 89 | C96: =IFERROR(VLOOKUP(B96,'Importer Data Fields'!C:D,2,0),"") | I96: lot | K96: =J96*H96 -> 0 | N96: =ROUND(L96*M96*H96,0) -> 0 | P96: =O96*N96 -> 0 | T96: =S96*Q96 -> 0 | V96: =H96*U96 -> 0 | W96: =V96+T96+P96+K96 -> 0
A97: =A96+1 -> 90 | C97: =IFERROR(VLOOKUP(B97,'Importer Data Fields'!C:D,2,0),"") | I97: lot | K97: =J97*H97 -> 0 | N97: =ROUND(L97*M97*H97,0) -> 0 | P97: =O97*N97 -> 0 | T97: =S97*Q97 -> 0 | V97: =H97*U97 -> 0 | W97: =V97+T97+P97+K97 -> 0
A98: =A97+1 -> 91 | B98: 08 Openings | K98: =J98*H98 -> 0 | N98: =ROUND(L98*M98*H98,0) -> 0 | P98: =O98*N98 -> 0 | T98: =S98*Q98 -> 0 | V98: =H98*U98 -> 0 | W98: =V98+T98+P98+K98 -> 0 | Y98: =SUM(W98:W112) -> 0
A99: =A98+1 -> 92 | B99: 08-5400 | C99: =IFERROR(VLOOKUP(B99,'Importer Data Fields'!C:D,2,0),"") -> Composite Windows | I99: lot | K99: =J99*H99 -> 0 | N99: =ROUND(L99*M99*H99,0) -> 0 | P99: =O99*N99 -> 0 | T99: =S99*Q99 -> 0 | V99: =H99*U99 -> 0 | W99: =V99+T99+P99+K99 -> 0
A100: =A99+1 -> 93 | B100: 08-3100 | C100: =IFERROR(VLOOKUP(B100,'Importer Data Fields'!C:D,2,0),"") -> Access Doors and Panels | I100: ea | K100: =J100*H100 -> 0 | N100: =ROUND(L100*M100*H100,0) -> 0 | P100: =O100*N100 -> 0 | T100: =S100*Q100 -> 0 | V100: =H100*U100 -> 0 | W100: =V100+T100+P100+K100 -> 0
A101: =A100+1 -> 94 | B101: 08-7100 | C101: =IFERROR(VLOOKUP(B101,'Importer Data Fields'!C:D,2,0),"") -> Door Hardware | I101: ea | K101: =J101*H101 -> 0 | N101: =ROUND(L101*M101*H101,0) -> 0 | P101: =O101*N101 -> 0 | T101: =S101*Q101 -> 0 | V101: =H101*U101 -> 0 | W101: =V101+T101+P101+K101 -> 0
A102: =A101+1 -> 95 | B102: 08-7100 | C102: =IFERROR(VLOOKUP(B102,'Importer Data Fields'!C:D,2,0),"") -> Door Hardware | I102: ea | K102: =J102*H102 -> 0 | N102: =ROUND(L102*M102*H102,0) -> 0 | P102: =O102*N102 -> 0 | T102: =S102*Q102 -> 0 | V102: =H102*U102 -> 0 | W102: =V102+T102+P102+K102 -> 0
...

Sheet Importer Data Fields
A1: Sub Job | B1: Sub Job Description | C1: Cost Code | D1: Cost Code Description | E1: Cost Type | F1: Cost Type Description | G1: BLI UOM | H1: BPQ UOM | I1: BOOLEAN
A2: None | B2: None | C2: None | D2: None | E2: E | F2: Equipment | G2: days | H2: ea | I2: True
C3: 00-000 | D3: Do Not Use | E3: L | F3: Labor | G3: hours | H3: ls | I3: False
C4: 01-3120 | D4: Vice President | E4: M | F4: Material | G4: months | H4: lf
C5: 01-3126 | D5: Pre-construction | E5: None | F5: None | G5: weeks | H5: m
C6: 01-3127 | D6: Sr. Project Manager | E6: R | F6: Contract Revenue | G6: years | H6: mm
C7: 01-3128 | D7: Project Manager | E7: S | F7: Subcontract | G7: ea | H7: m²
C8: 01-3129 | D8: Assistant Project Manager (APM) | E8: X | F8: Expense | G8: ls | H8: sf
C9: 01-3130 | D9: Project Engineer | G9: lf | H9: sy
C10: 01-3131 | D10: Field Engineer | G10: m | H10: cy
C11: 01-3132 | D11: Intern | G11: mm | H11: m³
C12: 01-3142 | D12: General Superintendent | G12: m² | H12: kg
C13: 01-3143 | D13: Sr. Superintendent | G13: sf | H13: lbs
C14: 01-3144 | D14: Superintendent | G14: sy | H14: t
C15: 01-3145 | D15: Assistant Superintendent | G15: cy | H15: ton
C16: 01-3223 | D16: Construction Layout | G16: m³
C17: 01-3236 | D17: Aerial & Periodic Drones | G17: kg
C18: 01-3238 | D18: Jobsite Security | G18: lbs
C19: 01-3245 | D19: Office Supplies | G19: t
C20: 01-3247 | D20: Printing & Copying | G20: ton
C21: 01-3249 | D21: Postage & Courier
C22: 01-3329 | D22: LEED Documentation
C23: 01-3514 | D23: Legal Fees
C24: 01-4123 | D24: Fees
C25: 01-4124 | D25: Sanitary Fees
C26: 01-4126 | D26: Permit Requirements
C27: 01-4523 | D27: Testing and Inspections
C28: 01-4533 | D28: Municipality Inspections
C29: 01-4613 | D29: Winter Conditions
C30: 01-5113 | D30: Temporary Electric
C31: 01-5116 | D31: Temporary Fire Protection
C32: 01-5119 | D32: Temporary Fuel
... C358: 55-0500 | D358: Contractor Fee

Sheet SubList
B1: Company | C1: Previsouly Sent Pricing | D1: Bid Decision | E1: Email Sent? Y/N | F1: Phone Call Follow Up? Y/N | G1: Bid Received? Y/N | H1: Contact | I1: Email | J1: Cell | K1: Price | L1: Comments | M1: Scope Includes? | N1: Scope Includes? | O1: Scope Includes? | P1: Scope Includes? | Q1: Scope Includes? | R1: Scope Includes? | S1: Scope Includes? | T1: Scope Includes? | U1: Scope Includes? | V1: Scope Includes?
B2: 01 General Conditions
A3: 1
A4: 2
A5: 3
A6: 4
A7: 5
B8: 02 Existing Conditions
A9: 1
A10: 2
A11: 3
A12: 4
A13: 5
B14: 03 Concrete | F14: Total Received: | G14: =COUNTIF(G15:G26,"yes") -> 5
A15: 1 | B15: CC Concrete | C15: Yes | D15: Bidding | E15: Yes | F15: No | G15: Yes | H15: C Weber | I15: cweber@ccconcrete.net | J15: 317-450-3317 | K15: 159921 | M15: Concrete
A16: 2 | B16: W.E. Beaty INC | C16: Yes | D16: Bidding | E16: Yes | F16: No | G16: No | H16: Matt Hillen | I16: mhillen@Webeatyinc.com | J16: 317-502-1331 | L16: Estimate to be sent by Wed 22nd | M16: Concrete
A17: 3 | B17: Custom Concrete | C17: No | D17: Bidding | E17: No | F17: Yes (spoke to) | G17: Yes | H17: Bryan Ness | I17: bryann@customconcrete.com | J17: 317-767-1439 | K17: 544500 | L17: Bryan is emailing Andrew questions | M17: Concrete
A18: 4 | B18: Karns INC | C18: Received Drawings but never sent price | D18: Bidding | E18: Yes | F18: Yes (spoke to) | G18: No | H18: Clayton Karns | I18: clay.karns@karnsinc.com | J18: 317-872-2529 | L18: Will have price sent back 1/17 | M18: Concrete
A19: 5 | B19: Trace Construction | C19: No | D19: Undecided | E19: Yes | F19: Yes (spoke to) | G19: No | H19: Caleb Shetterley | I19: cshetterley@traceconstruction.net | J19: 765-617-3534 / 317-362-0119 ext. 2003 | L19: Left voicemail 1/17.Not 100% sure if they will be bidding this project as of 1/8/25, will notifiy on building connected. | M19: Concrete
A20: 6 | B20: CEP Concrete Construction | C20: No | D20: Bidding | E20: No | F20: Yes (spoke to) | G20: Yes | H20: Bill Clemons | I20: bill@cepconcrete.com | J20: 317-534-8595 | K20: 146000 | L20: Received 1/17 | M20: Concrete
A21: 7 | B21: M&C Concrete | C21: No | D21: Bidding | E21: No | F21: Yes (no answer) | G21: No | H21: Tyler Sizelove | I21: tsizelove@mc-concrete.com | J21: 765-661-2482 | L21: Will need until the 20th-21st | M21: Concrete
A22: 8 | B22: Weber Concrete Construction | C22: No | D22: Not Bidding | E22: No | F22: Yes (spoke to) | G22: No | H22: Randy Fuller | I22: randyf@weberconcrete.com | J22: 317-447-2851 | L22: "We are a poured wall contractor" | M22: Concrete
A23: 9 | B23: Torrez Concrete | C23: No | D23: Undecided | E23: No | F23: Yes (no answer) | G23: No | H23: Torrez | I23: godlytorrez@gmail.com | J23: 317-993-8770 | L23: Left voicemail 1/17/2025 | M23: Concrete
A24: 10 | B24: Merrit Contracting INC | C24: No | D24: Bidding | E24: No | F24: Yes (spoke to) | G24: Yes | H24: Brent Wright | I24: bwright@merrittcontracting.com | J24: 317-646-3289 / 765-486-0947 | K24: 127755 | M24: Concrete
A25: 11 | B25: Howard Companies | C25: No | D25: Bidding | E25: Yes | F25: Yes (spoke to) | G25: Yes | H25: Josh Dillon | I25: jdillon@howardcompanies.com | J25: 317-363-5250 | K25: 129358.25 | L25: bid received 1/16
A26: 12 | B26: Allied Concrete Workers Inc | C26: Received Drawings but never sent price | D26: Bidding | E26: Yes | F26: Yes (no answer) | G26: No | H26: Terry Curtis | I26: terry@alliedcwinc.com | L26: Terry will have price sent back today | M26: Concrete
B27: 04 Masonry
A28: 1
A29: 2
A30: 3
A31: 4
A32: 5
B33: 05 Metals
A34: 1
A35: 2
A36: 3
A37: 4
A38: 5
B39: 06 Wood Plastics Composits
A40: 1
A41: 2
A42: 3
A43: 4
A44: 5
B45: 07 Thermal and Moisture Protection
A46: 1
A47: 2
A48: 3
A49: 4
A50: 5
B51: 08 Openings
A52: 1
A53: 2
A54: 3
A55: 4
A56: 5
B57: 09 Finishes
A58: 1
A59: 2
A60: 3
A61: 4
A62: 5
B63: 10 Specialties
A64: 1
A65: 2
A66: 3
A67: 4
A68: 5
B69: 11 Equipment
A70: 1
A71: 2
A72: 3
A73: 4
A74: 5
B75: 12 Furnishings
A76: 1
A77: 2
A78: 3
A79: 4
A80: 5
B81: 14 Conveying Equipment
A82: 1
A83: 2
A84: 3
A85: 4
A86: 5
B87: 21 Fire Suppression | F87: Total Received: | G87: =COUNTIF(G88:G94,"YES") -> 2
A88: 1 | B88: Brown Sprinkler | C88: No | D88: Bidding | E88: No | F88: Yes | G88: Yes | H88: Scott Schiesser | I88: sschiesser@brownsprinkler.com | J88: 317-775-7042 | K88: 113900 | L88: try and have sent back tomorrow 1/16/2025
A89: 2 | B89: Dalmatian Fire | C89: No | D89: Undecided | E89: No | F89: No | G89: No | H89: Christian Alspach | I89: calspach@dalmatianfire.net | L89: left voicmail 1/17
A90: 3 | B90: Integrity Fire Protection | C90: No | D90: Bidding | E90: No | F90: Yes | G90: Yes | H90: John Nayder | I90: john@integrityfirellc.com | J90: 317-361-9770 | K90: 108470 | L90: left voicemail 1/15
A91: 4 | B91: Performance Fire Protection | C91: No | D91: Bidding | E91: No | F91: Yes | G91: No | H91: Joe Schott | I91: joe.s@performancefp.com | J91: 463-202-2887 | L91: will have price sent back today 1/17
A92: 5 | B92: RSQ Fire Protection | C92: No | D92: Not Bidding | E92: No | F92: Yes | G92: No | H92: Corey Lee | I92: coreylee@rsqfp.com | J92: 1-888-777-9672 | L92: office was closed, front desk took my name and message
A93: 6 | B93: Ryan Fire Protection | C93: No | D93: Bidding | E93: No | F93: Yes | G93: No | H93: Alex Bell | I93: abell@ryanfp.com | J93: 463-290-9222 | L93: following up in the morning, Alex handed the estimate off to another emploee to work on
A94: 7 | B94: Siemens | C94: Yes | D94: Bidding | E94: No | F94: Yes | G94: No | H94: Christopher Lopez | I94: lopez.chris@siemens.com | J94: 463-239-6092 | L94: Will have price back before or after lunch today
B95: 22 Plumbing | F95: Total Received: | G95: =COUNTIF(G96:G106,"YES") -> 5
A96: 1 | B96: Fite | C96: Yes | D96: Bidding | E96: Yes | F96: No | G96: Yes | H96: Joe Thompson | I96: joet@fitellc.com | J96: 317-515-7383 | K96: 270000 | M96: Plumbing
A97: 2 | B97: Justin Dorsey | C97: Yes | D97: Bidding | E97: Yes | F97: No | G97: Yes | H97: Tom Tinkle | I97: tom@justindorseyplumbing.com | J97: 317-745-4830 | K97: 194100 | L97: Use original bid, Tom confirmed no changes needed | M97: Plumbing
A98: 3 | B98: Mission Mechanical | C98: Yes | D98: Bidding | E98: Yes | F98: No | G98: Yes | H98: Jon | I98: jon@missionmechanical.com | J98: 317-350-0188 | K98: 625200 | L98: HVAC & Plumbing | M98: Plumbing
A99: 4 | B99: McCurdy Mechanical | C99: Yes | D99: Bidding | E99: Yes | F99: No | G99: Yes | H99: Dave McCurdy | I99: dave@mccurdymech.com | J99: 317-556-4516 | K99: 315775
A100: 5 | B100: Real Mechanical | C100: No | D100: Not Bidding | E100: No | F100: Yes (no answer) | G100: No | H100: Mel Lamb | I100: mlamb@realmechanical.com | J100: 317-819-3036 | M100: Plumbing
...
